Workbook

Sheet EQUIPAMIENTO
A1: BUSCAR PRODUCTO: | J1: Hasta 20 coincidencias
A2: CODIGO | C2: FABRICA | D2: PUBLICO | E2: GANANCIA | F2: STOCK | G2: DESC. 5 % | H2: IVA 21 % | I2: FILA ORIGINAL | J2: Usá FILA ORIGINAL para modificar FABRICA (columna C) y STOCK (columna F) en la lista principal.
A3: {=IF(B1="","",_xlfn.LET(_xlpm.coincide,_xlfn.LAMBDA(_xlpm.t,_xlpm.p,OR(ISNUMBER(SEARCH(_xlpm.t,_xlpm.p)),OR(_xlfn.MAP(_xlfn.SEQUENCE(LEN(_xlpm.t)+1,,0),_xlfn.LAMBDA(_xlpm.k,ISNUMBER(SEARCH(LEFT(_xlpm.t,_xlpm.k)&"?"&MID(_xlpm.t,_xlpm.k+1,LEN(_xlpm.t)),_xlpm.p))))),OR(_xlfn.MAP(_xlfn.SEQUENCE(LEN(_xlpm.t)),_xlfn.LAMBDA(_xlpm.k,ISNUMBER(SEARCH(REPLACE(_xlpm.t,_xlpm.k,1,"?"),_xlpm.p))))),IF(LEN(_xlpm.t)>3,OR(_xlfn.MAP(_xlfn.SEQUENCE(LEN(_xlpm.t)),_xlfn.LAMBDA(_xlpm.k,ISNUMBER(SEARCH(REPLACE(_xlpm.t,_xlpm.k,1,""),_xlpm.p))))),FALSE))),_xlpm.terminos,_xlfn.TOCOL(_xlfn.TEXTSPLIT(LOWER(TRIM(B1))," "),1),_xlpm.productos,LOWER($B$27:$B$877),_xlpm.puntaje,_xlfn.BYROW(_xlpm.productos,_xlfn.LAMBDA(_xlpm.p,SUM(_xlfn.MAP(_xlpm.terminos,_xlfn.LAMBDA(_xlpm.t,--_xlpm.coincide(_xlpm.t,_xlpm.p)))))),_xlpm.datos,_xlfn.HSTACK($A$27:$H$877,ROW($B$27:$B$877)),IFERROR(_xlfn.TAKE(_xlfn._xlws.FILTER(_xlpm.datos,(_xlpm.puntaje=ROWS(_xlpm.terminos))*($B$27:$B$877<>"")),20),"NO ENCONTRADO")))}
A25: CODIGO | B25: PRODUCTO | C25: FABRICA | D25: PUBLICO | E25: GANANCIA | F25: STOCK | G25: DESC. 5 % | H25: IVA 21 % | L25: FABRICA BASE | M25: STOCK BASE
A26: K-17 | B26: ALFILER DE SEGURIDAD PARA PERNO | C26: =_xlfn.LET(_xlpm.x,_xlfn.XLOOKUP(ROW(),Ajustes!$A$5:$A$104,Ajustes!$D$5:$D$104,""),IF(_xlpm.x="",L26,_xlpm.x)) -> 1862 | D26: =C26*1.4 -> 2606.8 | E26: =D26-C26 -> 744.8 | F26: 10 | G26: =D26*0.95 -> 2476.46 | H26: =D26*1.21 -> 3154.228 | J26: =C26*F26 -> 18620 | K26: =E26*F26 -> 7448 | L26: 1862 | M26: 7
A27: BAF-6 | B27: ALFOMBRAS B-MATT AMAROK | C27: 186340 | D27: =C27*1.4 -> 260876 | E27: =D27-C27 -> 74536 | F27: 5 | G27: =D27*0.95 -> 247832.2 | H27: =D27*1.21 -> 315659.96 | J27: =C27*F27 -> 931700 | K27: =E27*F27 -> 372680 | L27: 145411 | M27: 0
A28: BAF-4 | B28: ALFOMBRAS B-MATT HILUX | C28: 186340 | D28: =C28*1.4 -> 260876 | E28: =D28-C28 -> 74536 | F28: 3 | G28: =D28*0.95 -> 247832.2 | H28: =D28*1.21 -> 315659.96 | J28: =C28*F28 -> 559020 | K28: =E28*F28 -> 223608 | L28: 145411 | M28: 1
A29: BAF-1 | B29: ALFOMBRAS B-MATT RANGER | C29: 186340 | D29: =C29*1.4 -> 260876 | E29: =D29-C29 -> 74536 | F29: 1 | G29: =D29*0.95 -> 247832.2 | H29: =D29*1.21 -> 315659.96 | J29: =C29*F29 -> 186340 | K29: =E29*F29 -> 74536 | L29: 145411 | M29: 0
A30: AB-50 | B30: AMORTIGUADOR LEVANTA CAPOT AMAROK | C30: =_xlfn.LET(_xlpm.x,_xlfn.XLOOKUP(ROW(),Ajustes!$A$5:$A$104,Ajustes!$D$5:$D$104,""),IF(_xlpm.x="",L30,_xlpm.x)) -> 139104 | D30: =C30*1.4 -> 194745.6 | E30: =D30-C30 -> 55641.6 | F30: =_xlfn.LET(_xlpm.x,_xlfn.XLOOKUP(ROW(),Ajustes!$A$5:$A$104,Ajustes!$E$5:$E$104,""),IF(_xlpm.x="",M30,_xlpm.x)) -> 2 | G30: =D30*0.95 -> 185008.32 | H30: =D30*1.21 -> 235642.18 | J30: =C30*F30 -> 278208 | K30: =E30*F30 -> 111283.2 | L30: 139104 | M30: 2
A31: AB-30 | B31: AMORTIGUADOR PORTON AMAROK S/ BARRA TORSION - IMPORTADO | C31: =_xlfn.LET(_xlpm.x,_xlfn.XLOOKUP(ROW(),Ajustes!$A$5:$A$104,Ajustes!$D$5:$D$104,""),IF(_xlpm.x="",L31,_xlpm.x)) -> 125850 | D31: =C31*1.4 -> 176190 | E31: =D31-C31 -> 50340 | F31: =_xlfn.LET(_xlpm.x,_xlfn.XLOOKUP(ROW(),Ajustes!$A$5:$A$104,Ajustes!$E$5:$E$104,""),IF(_xlpm.x="",M31,_xlpm.x)) -> 4 | G31: =D31*0.95 -> 167380.5 | H31: =D31*1.21 -> 213189.9 | J31: =C31*F31 -> 503400 | K31: =E31*F31 -> 201360 | L31: 125850 | M31: 4
A32: AB-31 | B32: AMORTIGUADOR PORTON CHEVROLET S-10 12+/24+ IMPORTADO | C32: 128464 | D32: =C32*1.4 -> 179849.6 | E32: =D32-C32 -> 51385.6 | F32: 1 | G32: =D32*0.95 -> 170857.12 | H32: =D32*1.21 -> 217618.02
A33: AB-38 | B33: AMORTIGUADOR PORTON FORD RANGER 23+ | C33: =_xlfn.LET(_xlpm.x,_xlfn.XLOOKUP(ROW(),Ajustes!$A$5:$A$104,Ajustes!$D$5:$D$104,""),IF(_xlpm.x="",L33,_xlpm.x)) -> 118734 | D33: =C33*1.4 -> 166227.6 | E33: =D33-C33 -> 47493.6 | F33: =_xlfn.LET(_xlpm.x,_xlfn.XLOOKUP(ROW(),Ajustes!$A$5:$A$104,Ajustes!$E$5:$E$104,""),IF(_xlpm.x="",M33,_xlpm.x)) -> 0 | G33: =D33*0.95 -> 157916.22 | H33: =D33*1.21 -> 201135.4 | J33: =C33*F33 -> 0 | K33: =E33*F33 -> 0 | L33: 118734 | M33: 0
A34: AB-32 | B34: AMORTIGUADOR PORTON TOYOTA HILUX 16+ - IMPORTADO (JUEGO) | C34: =_xlfn.LET(_xlpm.x,_xlfn.XLOOKUP(ROW(),Ajustes!$A$5:$A$104,Ajustes!$D$5:$D$104,""),IF(_xlpm.x="",L34,_xlpm.x)) -> 223781 | D34: =C34*1.4 -> 313293.4 | E34: =D34-C34 -> 89512.4 | F34: 0 | G34: =D34*0.95 -> 297628.73 | H34: =D34*1.21 -> 379085.01 | J34: =C34*F34 -> 0 | K34: =E34*F34 -> 0 | L34: 223781 | M34: 2
A35: K-27 | B35: ARO DE GOMA "ANTI-RUIDO" | C35: =_xlfn.LET(_xlpm.x,_xlfn.XLOOKUP(ROW(),Ajustes!$A$5:$A$104,Ajustes!$D$5:$D$104,""),IF(_xlpm.x="",L35,_xlpm.x)) -> 4279 | D35: =C35*1.4 -> 5990.6 | E35: =D35-C35 -> 1711.6 | F35: 28 | G35: =D35*0.95 -> 5691.07 | H35: =D35*1.21 -> 7248.626 | J35: =C35*F35 -> 119812 | K35: =E35*F35 -> 47924.8 | L35: 4279 | M35: 15
A36: B-30 | B36: BAR RACK ARCO REGULABLE UNIVERSAL | C36: =_xlfn.LET(_xlpm.x,_xlfn.XLOOKUP(ROW(),Ajustes!$A$5:$A$104,Ajustes!$D$5:$D$104,""),IF(_xlpm.x="",L36,_xlpm.x)) -> 251362 | D36: =C36*1.4 -> 351906.8 | E36: =D36-C36 -> 100544.8 | F36: 3 | G36: =D36*0.95 -> 334311.46 | H36: =D36*1.21 -> 425807.23 | K36: =E36*F36 -> 301634.4 | L36: 251362 | M36: 2
A37: BR-112 | B37: BARREROS DELANTEROS VW AMAROK 10+ (2 PIEZAS) | C37: =_xlfn.LET(_xlpm.x,_xlfn.XLOOKUP(ROW(),Ajustes!$A$5:$A$104,Ajustes!$D$5:$D$104,""),IF(_xlpm.x="",L37,_xlpm.x)) -> 55912 | D37: =C37*1.4 -> 78276.8 | E37: =D37-C37 -> 22364.8 | F37: 2 | G37: =D37*0.95 -> 74362.96 | H37: =D37*1.21 -> 94714.928 | J37: =C37*F37 -> 111824 | K37: =E37*F37 -> 44729.6 | L37: 55912
A38: BOX-370 | B38: BAUL DE TECHO PATAGONIA, CAPACIDAD 370 LITROS | C38: =_xlfn.LET(_xlpm.x,_xlfn.XLOOKUP(ROW(),Ajustes!$A$5:$A$104,Ajustes!$D$5:$D$104,""),IF(_xlpm.x="",L38,_xlpm.x)) -> 315366 | D38: =C38*1.4 -> 441512.4 | E38: =D38-C38 -> 126146.4 | F38: 0 | G38: =D38*0.95 -> 419436.78 | H38: =D38*1.21 -> 534230 | J38: =C38*F38 -> 0 | K38: =E38*F38 -> 0 | L38: 315366 | M38: 1
A39: BOX-16 | B39: BAUL LATERAL L.CONDUCTOR "EXPEDITION"-AGREGAR KIT | C39: =_xlfn.LET(_xlpm.x,_xlfn.XLOOKUP(ROW(),Ajustes!$A$5:$A$104,Ajustes!$D$5:$D$104,""),IF(_xlpm.x="",L39,_xlpm.x)) -> 341283 | D39: =C39*1.4 -> 477796.2 | E39: =D39-C39 -> 136513.2 | F39: =_xlfn.LET(_xlpm.x,_xlfn.XLOOKUP(ROW(),Ajustes!$A$5:$A$104,Ajustes!$E$5:$E$104,""),IF(_xlpm.x="",M39,_xlpm.x)) -> 1 | G39: =D39*0.95 -> 453906.39 | H39: =D39*1.21 -> 578133.4 | J39: =C39*F39 -> 341283 | K39: =E39*F39 -> 136513.2 | L39: 341283 | M39: 1
A40: BOX-40 | B40: BAUL METALICO "IRON-BOX" L95cm A48cm AL43cm 2 BOLSOS INTER. | C40: 482088 | D40: =C40*1.4 -> 674923.2 | E40: =D40-C40 -> 192835.2 | F40: 1 | G40: =D40*0.95 -> 641177.04 | H40: =D40*1.21 -> 816657.07 | J40: =C40*F40 -> 482088 | K40: =E40*F40 -> 192835.2 | L40: 445547 | M40: 0
A41: BOX-17 | B41: BAUL METALICO "IRON-BOX" LATERAL C/BOLSO | C41: =_xlfn.LET(_xlpm.x,_xlfn.XLOOKUP(ROW(),Ajustes!$A$5:$A$104,Ajustes!$D$5:$D$104,""),IF(_xlpm.x="",L41,_xlpm.x)) -> 272363 | D41: =C41*1.4 -> 381308.2 | E41: =D41-C41 -> 108945.2 | F41: =_xlfn.LET(_xlpm.x,_xlfn.XLOOKUP(ROW(),Ajustes!$A$5:$A$104,Ajustes!$E$5:$E$104,""),IF(_xlpm.x="",M41,_xlpm.x)) -> 1 | G41: =D41*0.95 -> 362242.79 | H41: =D41*1.21 -> 461382.92 | J41: =C41*F41 -> 272363 | K41: =E41*F41 -> 108945.2 | L41: 272363 | M41: 1
A42: BOX-4/5 | B42: BAUL PLAST."EXPEDICION" L. 97cm AN.55cm AL.45cm | C42: 445857 | D42: =C42*1.4 -> 624199.8 | E42: =D42-C42 -> 178342.8 | F42: 2 | G42: =D42*0.95 -> 592989.81 | H42: =D42*1.21 -> 755281.76 | J42: =C42*F42 -> 891714 | K42: =E42*F42 -> 356685.6 | L42: 420303 | M42: 1
A43: box-9/5 | B43: BAUL PLAST."EXPEDICION" L.130cm AN.55cm AL.45cm | C43: 620037 | D43: =C43*1.4 -> 868051.8 | E43: =D43-C43 -> 248014.8 | F43: 1 | G43: =D43*0.95 -> 824649.21 | H43: =D43*1.21 -> 1050342.7
A44: BOX-6/5 | B44: BAUL PLAST."EXPEDICION" L.140cm AN.55cm AL.45cm Base 98cm | C44: =_xlfn.LET(_xlpm.x,_xlfn.XLOOKUP(ROW(),Ajustes!$A$5:$A$104,Ajustes!$D$5:$D$104,""),IF(_xlpm.x="",L44,_xlpm.x)) -> 541472 | D44: =C44*1.4 -> 758060.8 | E44: =D44-C44 -> 216588.8 | F44: =_xlfn.LET(_xlpm.x,_xlfn.XLOOKUP(ROW(),Ajustes!$A$5:$A$104,Ajustes!$E$5:$E$104,""),IF(_xlpm.x="",M44,_xlpm.x)) -> 1 | G44: =D44*0.95 -> 720157.76 | H44: =D44*1.21 -> 917253.57 | J44: =C44*F44 -> 541472 | K44: =E44*F44 -> 216588.8 | L44: 541472 | M44: 1
A45: k-8/1 | B45: BOLITA CROMADA 1"7/8 VASTAGO 1" (2000 libras) | C45: =_xlfn.LET(_xlpm.x,_xlfn.XLOOKUP(ROW(),Ajustes!$A$5:$A$104,Ajustes!$D$5:$D$104,""),IF(_xlpm.x="",L45,_xlpm.x)) -> 19265 | D45: =C45*1.4 -> 26971 | E45: =D45-C45 -> 7706 | F45: 4 | G45: =D45*0.95 -> 25622.45 | H45: =D45*1.21 -> 32634.91 | J45: =C45*F45 -> 77060 | K45: =E45*F45 -> 30824 | L45: 19265 | M45: 6
A46: K-12/1 | B46: BOLITA CROMADA 2" VASTAGO 1" (3000 libras) | C46: =_xlfn.LET(_xlpm.x,_xlfn.XLOOKUP(ROW(),Ajustes!$A$5:$A$104,Ajustes!$D$5:$D$104,""),IF(_xlpm.x="",L46,_xlpm.x)) -> 22054 | D46: =C46*1.4 -> 30875.6 | E46: =D46-C46 -> 8821.6 | F46: =_xlfn.LET(_xlpm.x,_xlfn.XLOOKUP(ROW(),Ajustes!$A$5:$A$104,Ajustes!$E$5:$E$104,""),IF(_xlpm.x="",M46,_xlpm.x)) -> 3 | G46: =D46*0.95 -> 29331.82 | H46: =D46*1.21 -> 37359.476 | J46: =C46*F46 -> 66162 | K46: =E46*F46 -> 26464.8 | L46: 22054 | M46: 3
A47: K-8 | B47: BOLITA CROMADA 1" 7/8 VASTAGO 3/4 (2000 LIBRAS) | C47: =_xlfn.LET(_xlpm.x,_xlfn.XLOOKUP(ROW(),Ajustes!$A$5:$A$104,Ajustes!$D$5:$D$104,""),IF(_xlpm.x="",L47,_xlpm.x)) -> 15762 | D47: =C47*1.4 -> 22066.8 | E47: =D47-C47 -> 6304.8 | F47: 2 | G47: =D47*0.95 -> 20963.46 | H47: =D47*1.21 -> 26700.828 | J47: =C47*F47 -> 31524 | K47: =E47*F47 -> 12609.6 | L47: 15762 | M47: 1
A48: K-12 | B48: BOLITA CROMADA 2" VASTAGO 3/4 (3000 LIBRAS) | C48: =_xlfn.LET(_xlpm.x,_xlfn.XLOOKUP(ROW(),Ajustes!$A$5:$A$104,Ajustes!$D$5:$D$104,""),IF(_xlpm.x="",L48,_xlpm.x)) -> 18887 | D48: =C48*1.4 -> 26441.8 | E48: =D48-C48 -> 7554.8 | F48: =_xlfn.LET(_xlpm.x,_xlfn.XLOOKUP(ROW(),Ajustes!$A$5:$A$104,Ajustes!$E$5:$E$104,""),IF(_xlpm.x="",M48,_xlpm.x)) -> 0 | G48: =D48*0.95 -> 25119.71 | H48: =D48*1.21 -> 31994.578 | J48: =C48*F48 -> 0 | K48: =E48*F48 -> 0 | L48: 18887 | M48: 0
A49: BC-10 | B49: BOLSA PORTA CABEZAL TRACC | C49: =_xlfn.LET(_xlpm.x,_xlfn.XLOOKUP(ROW(),Ajustes!$A$5:$A$104,Ajustes!$D$5:$D$104,""),IF(_xlpm.x="",L49,_xlpm.x)) -> 3709 | D49: =C49*1.4 -> 5192.6 | E49: =D49-C49 -> 1483.6 | F49: =_xlfn.LET(_xlpm.x,_xlfn.XLOOKUP(ROW(),Ajustes!$A$5:$A$104,Ajustes!$E$5:$E$104,""),IF(_xlpm.x="",M49,_xlpm.x)) -> 2 | G49: =D49*0.95 -> 4932.97 | H49: =D49*1.21 -> 6283.046 | J49: =C49*F49 -> 7418 | K49: =E49*F49 -> 2967.2 | L49: 3709 | M49: 2
A50: BLS-1 | B50: BOLSO PARA CAJA DE CARGA ESTANCO UNIVERSAL (120X100X45CM) | C50: 134042 | D50: =C50*1.4 -> 187658.8 | E50: =D50-C50 -> 53616.8 | F50: 2 | G50: =D50*0.95 -> 178275.86 | H50: =D50*1.21 -> 227067.15
A51: BP-1 | B51: BURLETE PORTON AMAROK S-10 12+ HILUX 05-15 16+ FRONTIER 16+ | C51: =_xlfn.LET(_xlpm.x,_xlfn.XLOOKUP(ROW(),Ajustes!$A$5:$A$104,Ajustes!$D$5:$D$104,""),IF(_xlpm.x="",L51,_xlpm.x)) -> 55141 | D51: =C51*1.4 -> 77197.4 | E51: =D51-C51 -> 22056.4 | F51: 1 | G51: =D51*0.95 -> 73337.53 | H51: =D51*1.21 -> 93408.854 | J51: =C51*F51 -> 55141 | K51: =E51*F51 -> 22056.4 | L51: 55141 | M51: 2
A52: BAF-14 | B52: C.ALFOMBRAS B-MATT TOYOTA HILUX 05-15 D/C 3 PIEZAS | C52: 154252 | D52: =C52*1.4 -> 215952.8 | E52: =D52-C52 -> 61700.8 | F52: 1 | G52: =D52*0.95 -> 205155.16 | H52: =D52*1.21 -> 261302.89
A53: K-1 | B53: CABEZAL P/PERNO | C53: =_xlfn.LET(_xlpm.x,_xlfn.XLOOKUP(ROW(),Ajustes!$A$5:$A$104,Ajustes!$D$5:$D$104,""),IF(_xlpm.x="",L53,_xlpm.x)) -> 40001 | D53: =C53*1.4 -> 56001.4 | E53: =D53-C53 -> 16000.4 | F53: 2 | G53: =D53*0.95 -> 53201.33 | H53: =D53*1.21 -> 67761.694 | J53: =C53*F53 -> 80002 | K53: =E53*F53 -> 32000.8 | L53: 40001 | M53: 0
A54: K-3 | B54: CABEZAL ALTO P/PERNO | C54: 43282 | D54: =C54*1.4 -> 60594.8 | E54: =D54-C54 -> 17312.8 | F54: =_xlfn.LET(_xlpm.x,_xlfn.XLOOKUP(ROW(),Ajustes!$A$5:$A$104,Ajustes!$E$5:$E$104,""),IF(_xlpm.x="",M54,_xlpm.x)) -> 1 | G54: =D54*0.95 -> 57565.06 | H54: =D54*1.21 -> 73319.708 | J54: =C54*F54 -> 43282 | K54: =E54*F54 -> 17312.8 | L54: 42231 | M54: 1
A55: K-33 | B55: CABEZAL ALTO Y LARGO ESPECIAL P/PERNO | C55: =_xlfn.LET(_xlpm.x,_xlfn.XLOOKUP(ROW(),Ajustes!$A$5:$A$104,Ajustes!$D$5:$D$104,""),IF(_xlpm.x="",L55,_xlpm.x)) -> 50694 | D55: =C55*1.4 -> 70971.6 | E55: =D55-C55 -> 20277.6 | F55: =_xlfn.LET(_xlpm.x,_xlfn.XLOOKUP(ROW(),Ajustes!$A$5:$A$104,Ajustes!$E$5:$E$104,""),IF(_xlpm.x="",M55,_xlpm.x)) -> 1 | G55: =D55*0.95 -> 67423.02 | H55: =D55*1.21 -> 85875.636 | J55: =C55*F55 -> 50694 | K55: =E55*F55 -> 20277.6 | L55: 50694 | M55: 1
A56: K-23/3 | B56: CABEZAL FORD ORIG. P/PERNO (MAVERICK/RANGER/RAPT/F-150) | C56: 66876 | D56: =C56*1.4 -> 93626.4 | E56: =D56-C56 -> 26750.4 | F56: 2 | G56: =D56*0.95 -> 88945.08 | H56: =D56*1.21 -> 113287.94 | J56: =C56*F56 -> 133752 | K56: =E56*F56 -> 53500.8 | L56: 64304 | M56: 2
A57: K-23/1 | B57: CABEZAL MAXITRACC P/BOCHA K-8/1 (NO INCLUIDA) | C57: =_xlfn.LET(_xlpm.x,_xlfn.XLOOKUP(ROW(),Ajustes!$A$5:$A$104,Ajustes!$D$5:$D$104,""),IF(_xlpm.x="",L57,_xlpm.x)) -> 50052 | D57: =C57*1.4 -> 70072.8 | E57: =D57-C57 -> 20020.8 | F57: =_xlfn.LET(_xlpm.x,_xlfn.XLOOKUP(ROW(),Ajustes!$A$5:$A$104,Ajustes!$E$5:$E$104,""),IF(_xlpm.x="",M57,_xlpm.x)) -> 1 | G57: =D57*0.95 -> 66569.16 | H57: =D57*1.21 -> 84788.088 | J57: =C57*F57 -> 50052 | K57: =E57*F57 -> 20020.8 | L57: 50052 | M57: 1
A58: K-22 | B58: CABEZAL MAXITRACC P/PERNO | C58: =_xlfn.LET(_xlpm.x,_xlfn.XLOOKUP(ROW(),Ajustes!$A$5:$A$104,Ajustes!$D$5:$D$104,""),IF(_xlpm.x="",L58,_xlpm.x)) -> 63042 | D58: =C58*1.4 -> 88258.8 | E58: =D58-C58 -> 25216.8 | F58: 7 | G58: =D58*0.95 -> 83845.86 | H58: =D58*1.21 -> 106793.15 | J58: =C58*F58 -> 441294 | K58: =E58*F58 -> 176517.6 | L58: 63042 | M58: 8
A59: K-22-A/1 | B59: CABEZAL MAXITRACC P/PERNO "AMORTIGUADOR INTERNO" | C59: =_xlfn.LET(_xlpm.x,_xlfn.XLOOKUP(ROW(),Ajustes!$A$5:$A$104,Ajustes!$D$5:$D$104,""),IF(_xlpm.x="",L59,_xlpm.x)) -> 94978 | D59: =C59*1.4 -> 132969.2 | E59: =D59-C59 -> 37991.2 | F59: 8 | G59: =D59*0.95 -> 126320.74 | H59: =D59*1.21 -> 160892.73 | J59: =C59*F59 -> 759824 | K59: =E59*F59 -> 303929.6 | L59: 94978 | M59: 6
A60: K-35-A | B60: CABEZAL MAXITRACC ALTO Y LARG AMORT.INT P/BOCHA (NO INCLUIDA | C60: =_xlfn.LET(_xlpm.x,_xlfn.XLOOKUP(ROW(),Ajustes!$A$5:$A$104,Ajustes!$D$5:$D$104,""),IF(_xlpm.x="",L60,_xlpm.x)) -> 106192 | D60: =C60*1.4 -> 148668.8 | E60: =D60-C60 -> 42476.8 | F60: =_xlfn.LET(_xlpm.x,_xlfn.XLOOKUP(ROW(),Ajustes!$A$5:$A$104,Ajustes!$E$5:$E$104,""),IF(_xlpm.x="",M60,_xlpm.x)) -> 1 | G60: =D60*0.95 -> 141235.36 | H60: =D60*1.21 -> 179889.25 | J60: =C60*F60 -> 106192 | K60: =E60*F60 -> 42476.8 | L60: 106192 | M60: 1
A61: K-42 | B61: CABEZAL MAXITRACC ALTO Y LARGO ESPECIAL PERNO | C61: =_xlfn.LET(_xlpm.x,_xlfn.XLOOKUP(ROW(),Ajustes!$A$5:$A$104,Ajustes!$D$5:$D$104,""),IF(_xlpm.x="",L61,_xlpm.x)) -> 77473 | D61: =C61*1.4 -> 108462.2 | E61: =D61-C61 -> 30989.2 | F61: =_xlfn.LET(_xlpm.x,_xlfn.XLOOKUP(ROW(),Ajustes!$A$5:$A$104,Ajustes!$E$5:$E$104,""),IF(_xlpm.x="",M61,_xlpm.x)) -> 1 | G61: =D61*0.95 -> 103039.09 | H61: =D61*1.21 -> 131239.26 | J61: =C61*F61 -> 77473 | K61: =E61*F61 -> 30989.2 | L61: 77473 | M61: 1
A62: K-22 | B62: CABEZAL P/ PERNO MAXIT. COMPLETO(2PERNOS+2ALFILER+2GOMAS) | C62: =_xlfn.LET(_xlpm.x,_xlfn.XLOOKUP(ROW(),Ajustes!$A$5:$A$104,Ajustes!$D$5:$D$104,""),IF(_xlpm.x="",L62,_xlpm.x)) -> 94819 | D62: =C62*1.4 -> 132746.6 | E62: =D62-C62 -> 37927.6 | F62: =_xlfn.LET(_xlpm.x,_xlfn.XLOOKUP(ROW(),Ajustes!$A$5:$A$104,Ajustes!$E$5:$E$104,""),IF(_xlpm.x="",M62,_xlpm.x)) -> 2 | G62: =D62*0.95 -> 126109.27 | H62: =D62*1.21 -> 160623.39 | J62: =C62*F62 -> 189638 | K62: =E62*F62 -> 75855.2 | L62: 94819 | M62: 2
A63: K-1 | B63: CABEZAL TRACC COMPLETO(2 PERNOS+2 ALFILER+2 GOMAS) | C63: =_xlfn.LET(_xlpm.x,_xlfn.XLOOKUP(ROW(),Ajustes!$A$5:$A$104,Ajustes!$D$5:$D$104,""),IF(_xlpm.x="",L63,_xlpm.x)) -> 64560 | D63: =C63*1.4 -> 90384 | E63: =D63-C63 -> 25824 | F63: =_xlfn.LET(_xlpm.x,_xlfn.XLOOKUP(ROW(),Ajustes!$A$5:$A$104,Ajustes!$E$5:$E$104,""),IF(_xlpm.x="",M63,_xlpm.x)) -> 1 | G63: =D63*0.95 -> 85864.8 | H63: =D63*1.21 -> 109364.64 | J63: =C63*F63 -> 64560 | K63: =E63*F63 -> 25824 | L63: 64560 | M63: 1
A64: H-01 | B64: CAJA DE HERRAMIENTA CHICA | C64: =_xlfn.LET(_xlpm.x,_xlfn.XLOOKUP(ROW(),Ajustes!$A$5:$A$104,Ajustes!$D$5:$D$104,""),IF(_xlpm.x="",L64,_xlpm.x)) -> 20000 | D64: =C64*1.4 -> 28000 | E64: =D64-C64 -> 8000 | F64: =_xlfn.LET(_xlpm.x,_xlfn.XLOOKUP(ROW(),Ajustes!$A$5:$A$104,Ajustes!$E$5:$E$104,""),IF(_xlpm.x="",M64,_xlpm.x)) -> 1 | G64: =D64*0.95 -> 26600 | H64: =D64*1.21 -> 33880 | J64: =C64*F64 -> 20000 | K64: =E64*F64 -> 8000 | L64: 20000 | M64: 1
A65: CIB-100 | B65: CANASTO UNIVERSAL PARA JAULA ANTIVUELCO/RACK - INCLUIR KIT | C65: =_xlfn.LET(_xlpm.x,_xlfn.XLOOKUP(ROW(),Ajustes!$A$5:$A$104,Ajustes!$D$5:$D$104,""),IF(_xlpm.x="",L65,_xlpm.x)) -> 181200 | D65: =C65*1.4 -> 253680 | E65: =D65-C65 -> 72480 | F65: 2 | G65: =D65*0.95 -> 240996 | H65: =D65*1.21 -> 306952.8 | K65: =E65*F65 -> 144960 | L65: 181200 | M65: 1
A66: K-10 | B66: CARCAZA ABRAZA BOCHA 1" 7/8 (TORTUGA CHICA) | C66: =_xlfn.LET(_xlpm.x,_xlfn.XLOOKUP(ROW(),Ajustes!$A$5:$A$104,Ajustes!$D$5:$D$104,""),IF(_xlpm.x="",L66,_xlpm.x)) -> 17775 | D66: =C66*1.4 -> 24885 | E66: =D66-C66 -> 7110 | F66: =_xlfn.LET(_xlpm.x,_xlfn.XLOOKUP(ROW(),Ajustes!$A$5:$A$104,Ajustes!$E$5:$E$104,""),IF(_xlpm.x="",M66,_xlpm.x)) -> 1 | G66: =D66*0.95 -> 23640.75 | H66: =D66*1.21 -> 30110.85 | J66: =C66*F66 -> 17775 | K66: =E66*F66 -> 7110 | L66: 17775 | M66: 1
A67: K-18 | B67: CARCAZA ABRAZA BOCHA 2" (TORTUGA) | C67: =_xlfn.LET(_xlpm.x,_xlfn.XLOOKUP(ROW(),Ajustes!$A$5:$A$104,Ajustes!$D$5:$D$104,""),IF(_xlpm.x="",L67,_xlpm.x)) -> 25922 | D67: =C67*1.4 -> 36290.8 | E67: =D67-C67 -> 10368.8 | F67: 1 | G67: =D67*0.95 -> 34476.26 | H67: =D67*1.21 -> 43911.868 | J67: =C67*F67 -> 25922 | K67: =E67*F67 -> 10368.8 | L67: 25922 | M67: 2
A68: COB-140 | B68: COBERTOR CHEV. S-10 C/D B/P 12-24 (BRACCO) | C68: =_xlfn.LET(_xlpm.x,_xlfn.XLOOKUP(ROW(),Ajustes!$A$5:$A$104,Ajustes!$D$5:$D$104,""),IF(_xlpm.x="",L68,_xlpm.x)) -> 239609 | D68: =C68*1.4 -> 335452.6 | E68: =D68-C68 -> 95843.6 | F68: 0 | G68: =D68*0.95 -> 318679.97 | H68: =D68*1.21 -> 405897.65 | K68: =E68*F68 -> 0 | L68: 239609 | M68: 1
A69: COB-138 | B69: COBERTOR CHEVROLET S-10 C/D 25+ | C69: =_xlfn.LET(_xlpm.x,_xlfn.XLOOKUP(ROW(),Ajustes!$A$5:$A$104,Ajustes!$D$5:$D$104,""),IF(_xlpm.x="",L69,_xlpm.x)) -> 234906 | D69: =C69*1.4 -> 328868.4 | E69: =D69-C69 -> 93962.4 | F69: =_xlfn.LET(_xlpm.x,_xlfn.XLOOKUP(ROW(),Ajustes!$A$5:$A$104,Ajustes!$E$5:$E$104,""),IF(_xlpm.x="",M69,_xlpm.x)) -> 2 | G69: =D69*0.95 -> 312424.98 | H69: =D69*1.21 -> 397930.76 | J69: =C69*F69 -> 469812 | K69: =E69*F69 -> 187924.8 | L69: 234906 | M69: 2
A70: COB-188 | B70: COBERTOR FORD RANGER C/D B/P 23+ (BRACCO) | C70: =_xlfn.LET(_xlpm.x,_xlfn.XLOOKUP(ROW(),Ajustes!$A$5:$A$104,Ajustes!$D$5:$D$104,""),IF(_xlpm.x="",L70,_xlpm.x)) -> 266958 | D70: =C70*1.4 -> 373741.2 | E70: =D70-C70 -> 106783.2 | F70: 1 | G70: =D70*0.95 -> 355054.14 | H70: =D70*1.21 -> 452226.85 | J70: =C70*F70 -> 266958 | K70: =E70*F70 -> 106783.2 | L70: 266958 | M70: 2
A71: COB-113 | B71: COBERTOR TOYOTA HILUX C/D B/P 05-15 (BRACCO) | C71: 249193 | D71: =C71*1.4 -> 348870.2 | E71: =D71-C71 -> 99677.2 | F71: 1 | G71: =D71*0.95 -> 331426.69 | H71: =D71*1.21 -> 422132.94
A72: COB-146 | B72: COBERTOR TOYOTA HILUX C/D B/P 16+ (BRACCO) | C72: =_xlfn.LET(_xlpm.x,_xlfn.XLOOKUP(ROW(),Ajustes!$A$5:$A$104,Ajustes!$D$5:$D$104,""),IF(_xlpm.x="",L72,_xlpm.x)) -> 234906 | D72: =C72*1.4 -> 328868.4 | E72: =D72-C72 -> 93962.4 | F72: 3 | G72: =D72*0.95 -> 312424.98 | H72: =D72*1.21 -> 397930.76 | J72: =C72*F72 -> 704718 | K72: =E72*F72 -> 281887.2 | L72: 234906 | M72: 4
A73: COB-131 | B73: COBERTOR VW AMAROK C/D B/P 10+ (BRACCO) | C73: 249187 | D73: =C73*1.4 -> 348861.8 | E73: =D73-C73 -> 99674.8 | F73: 7 | G73: =D73*0.95 -> 331418.71 | H73: =D73*1.21 -> 422122.78 | J73: =C73*F73 -> 1744309 | K73: =E73*F73 -> 697723.6 | L73: 234906 | M73: 4
A74: V-68 | B74: CUBRE DIFERENCIAL VW AMAROK 10+ | C74: =_xlfn.LET(_xlpm.x,_xlfn.XLOOKUP(ROW(),Ajustes!$A$5:$A$104,Ajustes!$D$5:$D$104,""),IF(_xlpm.x="",L74,_xlpm.x)) -> 106831 | D74: =C74*1.4 -> 149563.4 | E74: =D74-C74 -> 42732.4 | F74: =_xlfn.LET(_xlpm.x,_xlfn.XLOOKUP(ROW(),Ajustes!$A$5:$A$104,Ajustes!$E$5:$E$104,""),IF(_xlpm.x="",M74,_xlpm.x)) -> 1 | G74: =D74*0.95 -> 142085.23 | H74: =D74*1.21 -> 180971.71 | J74: =C74*F74 -> 106831 | K74: =E74*F74 -> 42732.4 | L74: 106831 | M74: 1
A75: B-30/5 | B75: CUBRE LUNETA O BARRA LATERAL (1 UNIDAD) UNIVERSAL | C75: 65355 | D75: =C75*1.4 -> 91497 | E75: =D75-C75 -> 26142 | F75: 4 | G75: =D75*0.95 -> 86922.15 | H75: =D75*1.21 -> 110711.37
A76: V-102 | B76: DEFENSA AMAROK 17-24 TALAMPAYA 2"1/2 BLACK | C76: 187706 | D76: =C76*1.4 -> 262788.4 | E76: =D76-C76 -> 75082.4 | F76: 2 | G76: =D76*0.95 -> 249648.98 | H76: =D76*1.21 -> 317973.96
A77: AI-132 | B77: DEFENSA AMAROK 17-24 TALAMPAYA 2"1/2 INOX | C77: =_xlfn.LET(_xlpm.x,_xlfn.XLOOKUP(ROW(),Ajustes!$A$5:$A$104,Ajustes!$D$5:$D$104,""),IF(_xlpm.x="",L77,_xlpm.x)) -> 303144 | D77: =C77*1.4 -> 424401.6 | E77: =D77-C77 -> 121257.6 | F77: =_xlfn.LET(_xlpm.x,_xlfn.XLOOKUP(ROW(),Ajustes!$A$5:$A$104,Ajustes!$E$5:$E$104,""),IF(_xlpm.x="",M77,_xlpm.x)) -> 2 | G77: =D77*0.95 -> 403181.52 | H77: =D77*1.21 -> 513525.94 | J77: =C77*F77 -> 606288 | K77: =E77*F77 -> 242515.2 | L77: 303144 | M77: 2
A78: V-104 | B78: DEFENSA AMAROK 24+ TALAMPAYA 2"1/2 BLACK | C78: =_xlfn.LET(_xlpm.x,_xlfn.XLOOKUP(ROW(),Ajustes!$A$5:$A$104,Ajustes!$D$5:$D$104,""),IF(_xlpm.x="",L78,_xlpm.x)) -> 205073 | D78: =C78*1.4 -> 287102.2 | E78: =D78-C78 -> 82029.2 | F78: 3 | G78: =D78*0.95 -> 272747.09 | H78: =D78*1.21 -> 347393.66 | J78: =C78*F78 -> 615219 | K78: =E78*F78 -> 246087.6 | L78: 205073 | M78: 2
A79: AI-141 | B79: DEFENSA AMAROK 24+ TALAMPAYA 2"1/2 INOX | C79: =_xlfn.LET(_xlpm.x,_xlfn.XLOOKUP(ROW(),Ajustes!$A$5:$A$104,Ajustes!$D$5:$D$104,""),IF(_xlpm.x="",L79,_xlpm.x)) -> 346062 | D79: =C79*1.4 -> 484486.8 | E79: =D79-C79 -> 138424.8 | F79: =_xlfn.LET(_xlpm.x,_xlfn.XLOOKUP(ROW(),Ajustes!$A$5:$A$104,Ajustes!$E$5:$E$104,""),IF(_xlpm.x="",M79,_xlpm.x)) -> 2 | G79: =D79*0.95 -> 460262.46 | H79: =D79*1.21 -> 586229.03 | J79: =C79*F79 -> 692124 | K79: =E79*F79 -> 276849.6 | L79: 346062 | M79: 2
A80: T-83 | B80: DEFENSA HILUX 16-18 / 21+ TALAMPAYA BLACK | C80: =_xlfn.LET(_xlpm.x,_xlfn.XLOOKUP(ROW(),Ajustes!$A$5:$A$104,Ajustes!$D$5:$D$104,""),IF(_xlpm.x="",L80,_xlpm.x)) -> 173505 | D80: =C80*1.4 -> 242907 | E80: =D80-C80 -> 69402 | F80: 2 | G80: =D80*0.95 -> 230761.65 | H80: =D80*1.21 -> 293917.47 | J80: =C80*F80 -> 347010 | K80: =E80*F80 -> 138804 | L80: 173505 | M80: 2
A81: AI-138 | B81: DEFENSA HILUX 16-18 / 21+ TALAMPAYA INOX | C81: =_xlfn.LET(_xlpm.x,_xlfn.XLOOKUP(ROW(),Ajustes!$A$5:$A$104,Ajustes!$D$5:$D$104,""),IF(_xlpm.x="",L81,_xlpm.x)) -> 297040 | D81: =C81*1.4 -> 415856 | E81: =D81-C81 -> 118816 | F81: =_xlfn.LET(_xlpm.x,_xlfn.XLOOKUP(ROW(),Ajustes!$A$5:$A$104,Ajustes!$E$5:$E$104,""),IF(_xlpm.x="",M81,_xlpm.x)) -> 2 | G81: =D81*0.95 -> 395063.2 | H81: =D81*1.21 -> 503185.76 | J81: =C81*F81 -> 594080 | K81: =E81*F81 -> 237632 | L81: 297040 | M81: 2
A82: T-72 | B82: DEFENSA HILUX/SW4 05-15 TALAMPAYA BLACK | C82: 187794 | D82: =C82*1.4 -> 262911.6 | E82: =D82-C82 -> 75117.6 | F82: 1 | G82: =D82*0.95 -> 249766.02 | H82: =D82*1.21 -> 318123.04
A83: AI-122 | B83: DEFENSA HILUX/SW4 05-15 TALAMPAYA INOX | C83: 315270 | D83: =C83*1.4 -> 441378 | E83: =D83-C83 -> 126108 | F83: 2 | G83: =D83*0.95 -> 419309.1 | H83: =D83*1.21 -> 534067.38
A84: N-50 | B84: DEFENSA NISSAN FRONTIER 16+ ALASKAN 20+ TALAMPAYA BLACK | C84: =_xlfn.LET(_xlpm.x,_xlfn.XLOOKUP(ROW(),Ajustes!$A$5:$A$104,Ajustes!$D$5:$D$104,""),IF(_xlpm.x="",L84,_xlpm.x)) -> 173478 | D84: =C84*1.4 -> 242869.2 | E84: =D84-C84 -> 69391.2 | F84: =_xlfn.LET(_xlpm.x,_xlfn.XLOOKUP(ROW(),Ajustes!$A$5:$A$104,Ajustes!$E$5:$E$104,""),IF(_xlpm.x="",M84,_xlpm.x)) -> 1 | G84: =D84*0.95 -> 230725.74 | H84: =D84*1.21 -> 293871.73 | J84: =C84*F84 -> 173478 | K84: =E84*F84 -> 69391.2 | L84: 173478 | M84: 1
A85: AI-129 | B85: DEFENSA NISSAN FRONTIER 16+ALASKAN 20+TALAMPAYA INOX | C85: =_xlfn.LET(_xlpm.x,_xlfn.XLOOKUP(ROW(),Ajustes!$A$5:$A$104,Ajustes!$D$5:$D$104,""),IF(_xlpm.x="",L85,_xlpm.x)) -> 291373 | D85: =C85*1.4 -> 407922.2 | E85: =D85-C85 -> 116549.2 | F85: =_xlfn.LET(_xlpm.x,_xlfn.XLOOKUP(ROW(),Ajustes!$A$5:$A$104,Ajustes!$E$5:$E$104,""),IF(_xlpm.x="",M85,_xlpm.x)) -> 1 | G85: =D85*0.95 -> 387526.09 | H85: =D85*1.21 -> 493585.86 | J85: =C85*F85 -> 291373 | K85: =E85*F85 -> 116549.2 | L85: 291373 | M85: 1
A86: F-118 | B86: DEFENSA RANGER 12-22 TALAMPAYA 2"1/2 BLACK | C86: 189562 | D86: =C86*1.4 -> 265386.8 | E86: =D86-C86 -> 75824.8 | F86: 1 | G86: =D86*0.95 -> 252117.46 | H86: =D86*1.21 -> 321118.03
A87: AI-127 | B87: DEFENSA RANGER 12-22 TALAMPAYA 2"1/2 INOX | C87: =_xlfn.LET(_xlpm.x,_xlfn.XLOOKUP(ROW(),Ajustes!$A$5:$A$104,Ajustes!$D$5:$D$104,""),IF(_xlpm.x="",L87,_xlpm.x)) -> 291373 | D87: =C87*1.4 -> 407922.2 | E87: =D87-C87 -> 116549.2 | F87: 1 | G87: =D87*0.95 -> 387526.09 | H87: =D87*1.21 -> 493585.86 | J87: =C87*F87 -> 291373 | K87: =E87*F87 -> 116549.2 | L87: 291373 | M87: 0
A88: F-156 | B88: DEFENSA RANGER/EVEREST 23+ TALAMPAYA 2"1/2 BLACK | C88: =_xlfn.LET(_xlpm.x,_xlfn.XLOOKUP(ROW(),Ajustes!$A$5:$A$104,Ajustes!$D$5:$D$104,""),IF(_xlpm.x="",L88,_xlpm.x)) -> 175197 | D88: =C88*1.4 -> 245275.8 | E88: =D88-C88 -> 70078.8 | F88: 0 | G88: =D88*0.95 -> 233012.01 | H88: =D88*1.21 -> 296783.72 | J88: =C88*F88 -> 0 | K88: =E88*F88 -> 0 | L88: 175197 | M88: 1
A89: AI-140 | B89: DEFENSA RANGER/EVEREST 23+ TALAMPAYA 2"1/2 INOX | C89: =_xlfn.LET(_xlpm.x,_xlfn.XLOOKUP(ROW(),Ajustes!$A$5:$A$104,Ajustes!$D$5:$D$104,""),IF(_xlpm.x="",L89,_xlpm.x)) -> 291373 | D89: =C89*1.4 -> 407922.2 | E89: =D89-C89 -> 116549.2 | F89: =_xlfn.LET(_xlpm.x,_xlfn.XLOOKUP(ROW(),Ajustes!$A$5:$A$104,Ajustes!$E$5:$E$104,""),IF(_xlpm.x="",M89,_xlpm.x)) -> 1 | G89: =D89*0.95 -> 387526.09 | H89: =D89*1.21 -> 493585.86 | J89: =C89*F89 -> 291373 | K89: =E89*F89 -> 116549.2 | L89: 291373 | M89: 1
A90: AI-143 | B90: DEFENSA S-10 16+ LTZ/HIGH COUNTRY TALAMPAYA 2"1/2 INOX | C90: =_xlfn.LET(_xlpm.x,_xlfn.XLOOKUP(ROW(),Ajustes!$A$5:$A$104,Ajustes!$D$5:$D$104,""),IF(_xlpm.x="",L90,_xlpm.x)) -> 293116 | D90: =C90*1.4 -> 410362.4 | E90: =D90-C90 -> 117246.4 | F90: =_xlfn.LET(_xlpm.x,_xlfn.XLOOKUP(ROW(),Ajustes!$A$5:$A$104,Ajustes!$E$5:$E$104,""),IF(_xlpm.x="",M90,_xlpm.x)) -> 1 | G90: =D90*0.95 -> 389844.28 | H90: =D90*1.21 -> 496538.5 | J90: =C90*F90 -> 293116 | K90: =E90*F90 -> 117246.4 | L90: 293116 | M90: 1
A91: AI-142 | B91: DEFENSA S-10 16+(NO LTZ/HC)/TBLZR 16+ TALAMPAYA 2"1/2 INOX | C91: =_xlfn.LET(_xlpm.x,_xlfn.XLOOKUP(ROW(),Ajustes!$A$5:$A$104,Ajustes!$D$5:$D$104,""),IF(_xlpm.x="",L91,_xlpm.x)) -> 291208 | D91: =C91*1.4 -> 407691.2 | E91: =D91-C91 -> 116483.2 | F91: =_xlfn.LET(_xlpm.x,_xlfn.XLOOKUP(ROW(),Ajustes!$A$5:$A$104,Ajustes!$E$5:$E$104,""),IF(_xlpm.x="",M91,_xlpm.x)) -> 1 | G91: =D91*0.95 -> 387306.64 | H91: =D91*1.21 -> 493306.35 | J91: =C91*F91 -> 291208 | K91: =E91*F91 -> 116483.2 | L91: 291208 | M91: 1
A92: CH-64 | B92: DEFENSA S-10 16+(NO LTZ/HC)/TBLZR 16+ TALAMPAYA 2"1/2 BLACK | C92: 187760 | D92: =C92*1.4 -> 262864 | E92: =D92-C92 -> 75104 | F92: 1 | G92: =D92*0.95 -> 249720.8 | H92: =D92*1.21 -> 318065.44
A93: CH-66 | B93: DEFENSA S-10 25+ LTZ/HIGH COUNTRY TALAMPAYA 2"1/2 BLACK | C93: 187760 | D93: =C93*1.4 -> 262864 | E93: =D93-C93 -> 75104 | F93: 1 | G93: =D93*0.95 -> 249720.8 | H93: =D93*1.21 -> 318065.44
A94: B-3061 | B94: DEFLEC CAPOT CHEV. S-10 16+ (DEFLEC.CAPOT) | C94: =_xlfn.LET(_xlpm.x,_xlfn.XLOOKUP(ROW(),Ajustes!$A$5:$A$104,Ajustes!$D$5:$D$104,""),IF(_xlpm.x="",L94,_xlpm.x)) -> 64862 | D94: =C94*1.4 -> 90806.8 | E94: =D94-C94 -> 25944.8 | F94: 1 | G94: =D94*0.95 -> 86266.46 | H94: =D94*1.21 -> 109876.23 | J94: =C94*F94 -> 64862 | K94: =E94*F94 -> 25944.8 | L94: 64862 | M94: 1
A95: B-3059 | B95: DEFLEC CAPOT FORD RANGER 16/22 | C95: 67954 | D95: =C95*1.4 -> 95135.6 | E95: =D95-C95 -> 27181.6 | F95: 1 | G95: =D95*0.95 -> 90378.82 | H95: =D95*1.21 -> 115114.08
A96: B-3059 | B96: DEFLEC CAPOT FORD RANGER 16/22 | C96: 67954 | D96: =C96*1.4 -> 95135.6 | E96: =D96-C96 -> 27181.6 | F96: 1 | G96: =D96*0.95 -> 90378.82 | H96: =D96*1.21 -> 115114.08
A97: B-3063-FU | B97: DEFLEC CAPOT FORD RANGER 2023+ | C97: =_xlfn.LET(_xlpm.x,_xlfn.XLOOKUP(ROW(),Ajustes!$A$5:$A$104,Ajustes!$D$5:$D$104,""),IF(_xlpm.x="",L97,_xlpm.x)) -> 50117 | D97: =C97*1.4 -> 70163.8 | E97: =D97-C97 -> 20046.8 | F97: =_xlfn.LET(_xlpm.x,_xlfn.XLOOKUP(ROW(),Ajustes!$A$5:$A$104,Ajustes!$E$5:$E$104,""),IF(_xlpm.x="",M97,_xlpm.x)) -> 1 | G97: =D97*0.95 -> 66655.61 | H97: =D97*1.21 -> 84898.198 | J97: =C97*F97 -> 50117 | K97: =E97*F97 -> 20046.8 | L97: 50117 | M97: 1
A98: B-3023 | B98: DEFLEC CAPOT TOYOTA HILUX 12-15 | C98: =_xlfn.LET(_xlpm.x,_xlfn.XLOOKUP(ROW(),Ajustes!$A$5:$A$104,Ajustes!$D$5:$D$104,""),IF(_xlpm.x="",L98,_xlpm.x)) -> 70222 | D98: =C98*1.4 -> 98310.8 | E98: =D98-C98 -> 28088.8 | F98: 2 | G98: =D98*0.95 -> 93395.26 | H98: =D98*1.21 -> 118956.07 | J98: =C98*F98 -> 140444 | K98: =E98*F98 -> 56177.6 | L98: 70222 | M98: 1
A99: B-3048-FU | B99: DEFLEC CAPOT TOYOTA HILUX 16+ | C99: =_xlfn.LET(_xlpm.x,_xlfn.XLOOKUP(ROW(),Ajustes!$A$5:$A$104,Ajustes!$D$5:$D$104,""),IF(_xlpm.x="",L99,_xlpm.x)) -> 78500 | D99: =C99*1.4 -> 109900 | E99: =D99-C99 -> 31400 | F99: =_xlfn.LET(_xlpm.x,_xlfn.XLOOKUP(ROW(),Ajustes!$A$5:$A$104,Ajustes!$E$5:$E$104,""),IF(_xlpm.x="",M99,_xlpm.x)) -> 2 | G99: =D99*0.95 -> 104405 | H99: =D99*1.21 -> 132979 | J99: =C99*F99 -> 157000 | K99: =E99*F99 -> 62800 | L99: 78500 | M99: 2
A100: B-3049 | B100: DEFLEC CAPOT TOYOTA HILUX CORTO 16+ | C100: =_xlfn.LET(_xlpm.x,_xlfn.XLOOKUP(ROW(),Ajustes!$A$5:$A$104,Ajustes!$D$5:$D$104,""),IF(_xlpm.x="",L100,_xlpm.x)) -> 40816 | D100: =C100*1.4 -> 57142.4 | E100: =D100-C100 -> 16326.4 | F100: =_xlfn.LET(_xlpm.x,_xlfn.XLOOKUP(ROW(),Ajustes!$A$5:$A$104,Ajustes!$E$5:$E$104,""),IF(_xlpm.x="",M100,_xlpm.x)) -> 1 | G100: =D100*0.95 -> 54285.28 | H100: =D100*1.21 -> 69142.304 | J100: =C100*F100 -> 40816 | K100: =E100*F100 -> 16326.4 | L100: 40816 | M100: 1
A101: B-3060 | B101: DEFLEC CAPOT VW AMAROK 10-23 (DEFL. CAPOT) | C101: =_xlfn.LET(_xlpm.x,_xlfn.XLOOKUP(ROW(),Ajustes!$A$5:$A$104,Ajustes!$D$5:$D$104,""),IF(_xlpm.x="",L101,_xlpm.x)) -> 63634 | D101: =C101*1.4 -> 89087.6 | E101: =D101-C101 -> 25453.6 | F101: =_xlfn.LET(_xlpm.x,_xlfn.XLOOKUP(ROW(),Ajustes!$A$5:$A$104,Ajustes!$E$5:$E$104,""),IF(_xlpm.x="",M101,_xlpm.x)) -> 2 | G101: =D101*0.95 -> 84633.22 | H101: =D101*1.21 -> 107796 | J101: =C101*F101 -> 127268 | K101: =E101*F101 -> 50907.2 | L101: 63634 | M101: 2
A102: B-3066-FU | B102: DEFLEC CAPOT VW AMAROK 24+ (DEFL. CAPOT) | C102: =_xlfn.LET(_xlpm.x,_xlfn.XLOOKUP(ROW(),Ajustes!$A$5:$A$104,Ajustes!$D$5:$D$104,""),IF(_xlpm.x="",L102,_xlpm.x)) -> 57030 | D102: =C102*1.4 -> 79842 | E102: =D102-C102 -> 22812 | F102: 4 | G102: =D102*0.95 -> 75849.9 | H102: =D102*1.21 -> 96608.82 | J102: =C102*F102 -> 228120 | K102: =E102*F102 -> 91248 | L102: 57030 | M102: 1
A103: B-3066-M | B103: DEFLEC CAPOT VW AMAROK 24+ (MATE)(DEFL. CAPOT) | C103: =_xlfn.LET(_xlpm.x,_xlfn.XLOOKUP(ROW(),Ajustes!$A$5:$A$104,Ajustes!$D$5:$D$104,""),IF(_xlpm.x="",L103,_xlpm.x)) -> 91247 | D103: =C103*1.4 -> 127745.8 | E103: =D103-C103 -> 36498.8 | F103: 2 | G103: =D103*0.95 -> 121358.51 | H103: =D103*1.21 -> 154572.42 | J103: =C103*F103 -> 182494 | K103: =E103*F103 -> 72997.6 | L103: 91247 | M103: 3
A104: B-1628-TA | B104: DEFLEC VENTANILLA ALASKAN / FRONTIER 2021+ JGO TRASERO | C104: =_xlfn.LET(_xlpm.x,_xlfn.XLOOKUP(ROW(),Ajustes!$A$5:$A$104,Ajustes!$D$5:$D$104,""),IF(_xlpm.x="",L104,_xlpm.x)) -> 34060 | D104: =C104*1.4 -> 47684 | E104: =D104-C104 -> 13624 | F104: =_xlfn.LET(_xlpm.x,_xlfn.XLOOKUP(ROW(),Ajustes!$A$5:$A$104,Ajustes!$E$5:$E$104,""),IF(_xlpm.x="",M104,_xlpm.x)) -> 1 | G104: =D104*0.95 -> 45299.8 | H104: =D104*1.21 -> 57697.64 | J104: =C104*F104 -> 34060 | K104: =E104*F104 -> 13624 | L104: 34060 | M104: 1
A105: B-1518-TA | B105: DEFLEC VENTANILLA CHEV. S-10 12+ (JGO.TRASERO ADHESIV) | C105: =_xlfn.LET(_xlpm.x,_xlfn.XLOOKUP(ROW(),Ajustes!$A$5:$A$104,Ajustes!$D$5:$D$104,""),IF(_xlpm.x="",L105,_xlpm.x)) -> 32324 | D105: =C105*1.4 -> 45253.6 | E105: =D105-C105 -> 12929.6 | F105: 0 | G105: =D105*0.95 -> 42990.92 | H105: =D105*1.21 -> 54756.856 | J105: =C105*F105 -> 0 | K105: =E105*F105 -> 0 | L105: 32324 | M105: 1
A106: B-1518-A | B106: DEFLEC VENTANILLA CHEV. S-10 12+ (JGO.DELANT.ADHESIVO) | C106: =_xlfn.LET(_xlpm.x,_xlfn.XLOOKUP(ROW(),Ajustes!$A$5:$A$104,Ajustes!$D$5:$D$104,""),IF(_xlpm.x="",L106,_xlpm.x)) -> 35007 | D106: =C106*1.4 -> 49009.8 | E106: =D106-C106 -> 14002.8 | F106: 0 | G106: =D106*0.95 -> 46559.31 | H106: =D106*1.21 -> 59301.858 | J106: =C106*F106 -> 0 | K106: =E106*F106 -> 0 | L106: 35007 | M106: 1
A107: B-1332-TA | B107: DEFLEC VENTANILLA FORD RANGER 23+ (JGO ADHESIVO TRAS) | C107: =_xlfn.LET(_xlpm.x,_xlfn.XLOOKUP(ROW(),Ajustes!$A$5:$A$104,Ajustes!$D$5:$D$104,""),IF(_xlpm.x="",L107,_xlpm.x)) -> 30342 | D107: =C107*1.4 -> 42478.8 | E107: =D107-C107 -> 12136.8 | F107: =_xlfn.LET(_xlpm.x,_xlfn.XLOOKUP(ROW(),Ajustes!$A$5:$A$104,Ajustes!$E$5:$E$104,""),IF(_xlpm.x="",M107,_xlpm.x)) -> 1 | G107: =D107*0.95 -> 40354.86 | H107: =D107*1.21 -> 51399.348 | J107: =C107*F107 -> 30342 | K107: =E107*F107 -> 12136.8 | L107: 30342 | M107: 1
A108: B-1332-A | B108: DEFLEC VENTANILLA FORD RANGER 23+ (JGO DELANT ADHESIVO) | C108: =_xlfn.LET(_xlpm.x,_xlfn.XLOOKUP(ROW(),Ajustes!$A$5:$A$104,Ajustes!$D$5:$D$104,""),IF(_xlpm.x="",L108,_xlpm.x)) -> 38257 | D108: =C108*1.4 -> 53559.8 | E108: =D108-C108 -> 15302.8 | F108: =_xlfn.LET(_xlpm.x,_xlfn.XLOOKUP(ROW(),Ajustes!$A$5:$A$104,Ajustes!$E$5:$E$104,""),IF(_xlpm.x="",M108,_xlpm.x)) -> 1 | G108: =D108*0.95 -> 50881.81 | H108: =D108*1.21 -> 64807.358 | J108: =C108*F108 -> 38257 | K108: =E108*F108 -> 15302.8 | L108: 38257 | M108: 1
A109: B-2108 | B109: DEFLEC VENTANILLA HILUX 05+ C/S (JGO.DELANT.COLIZA) | C109: =_xlfn.LET(_xlpm.x,_xlfn.XLOOKUP(ROW(),Ajustes!$A$5:$A$104,Ajustes!$D$5:$D$104,""),IF(_xlpm.x="",L109,_xlpm.x)) -> 38015 | D109: =C109*1.4 -> 53221 | E109: =D109-C109 -> 15206 | F109: =_xlfn.LET(_xlpm.x,_xlfn.XLOOKUP(ROW(),Ajustes!$A$5:$A$104,Ajustes!$E$5:$E$104,""),IF(_xlpm.x="",M109,_xlpm.x)) -> 1 | G109: =D109*0.95 -> 50559.95 | H109: =D109*1.21 -> 64397.41 | J109: =C109*F109 -> 38015 | K109: =E109*F109 -> 15206 | L109: 38015 | M109: 1
A110: B-2109-A | B110: DEFLEC VENTANILLA HILUX 05-15 D/C (JGO.DELANT.ADHESIVO) | C110: =_xlfn.LET(_xlpm.x,_xlfn.XLOOKUP(ROW(),Ajustes!$A$5:$A$104,Ajustes!$D$5:$D$104,""),IF(_xlpm.x="",L110,_xlpm.x)) -> 36474 | D110: =C110*1.4 -> 51063.6 | E110: =D110-C110 -> 14589.6 | F110: 2 | G110: =D110*0.95 -> 48510.42 | H110: =D110*1.21 -> 61786.956 | J110: =C110*F110 -> 72948 | K110: =E110*F110 -> 29179.2 | L110: 36474 | M110: 1
A111: B-2110-A | B111: DEFLEC VENTANILLA HILUX 05-15 D/C (JGO.TRASERO ADHESIV) | C111: =_xlfn.LET(_xlpm.x,_xlfn.XLOOKUP(ROW(),Ajustes!$A$5:$A$104,Ajustes!$D$5:$D$104,""),IF(_xlpm.x="",L111,_xlpm.x)) -> 33458 | D111: =C111*1.4 -> 46841.2 | E111: =D111-C111 -> 13383.2 | F111: 2 | G111: =D111*0.95 -> 44499.14 | H111: =D111*1.21 -> 56677.852 | K111: =E111*F111 -> 26766.4 | L111: 33458 | M111: 1
A112: B-2113-A | B112: DEFLEC VENTANILLA HILUX 16+ D/C (JGO.DELANT.ADHESIVO) | C112: =_xlfn.LET(_xlpm.x,_xlfn.XLOOKUP(ROW(),Ajustes!$A$5:$A$104,Ajustes!$D$5:$D$104,""),IF(_xlpm.x="",L112,_xlpm.x)) -> 39709 | D112: =C112*1.4 -> 55592.6 | E112: =D112-C112 -> 15883.6 | F112: 3 | G112: =D112*0.95 -> 52812.97 | H112: =D112*1.21 -> 67267.046 | J112: =C112*F112 -> 119127 | K112: =E112*F112 -> 47650.8 | L112: 39709 | M112: 1
A113: B-2113-TA | B113: DEFLEC VENTANILLA HILUX 16+ D/C (JGO.TRASERO ADHESIV) | C113: =_xlfn.LET(_xlpm.x,_xlfn.XLOOKUP(ROW(),Ajustes!$A$5:$A$104,Ajustes!$D$5:$D$104,""),IF(_xlpm.x="",L113,_xlpm.x)) -> 32332 | D113: =C113*1.4 -> 45264.8 | E113: =D113-C113 -> 12932.8 | F113: 3 | G113: =D113*0.95 -> 43001.56 | H113: =D113*1.21 -> 54770.408 | J113: =C113*F113 -> 96996 | K113: =E113*F113 -> 38798.4 | L113: 32332 | M113: 1
A114: B-1830-A | B114: DEFLEC VENTANILLA VW AMAROK 10-24 (JGO.DELANT ADHESIVO) | C114: =_xlfn.LET(_xlpm.x,_xlfn.XLOOKUP(ROW(),Ajustes!$A$5:$A$104,Ajustes!$D$5:$D$104,""),IF(_xlpm.x="",L114,_xlpm.x)) -> 35007 | D114: =C114*1.4 -> 49009.8 | E114: =D114-C114 -> 14002.8 | F114: 3 | G114: =D114*0.95 -> 46559.31 | H114: =D114*1.21 -> 59301.858 | J114: =C114*F114 -> 105021 | K114: =E114*F114 -> 42008.4 | L114: 35007 | M114: 2
A115: B-1830-TA | B115: DEFLEC VENTANILLA VW AMAROK 10-24 (JGO.TRAS. ADHESIVO) | C115: =_xlfn.LET(_xlpm.x,_xlfn.XLOOKUP(ROW(),Ajustes!$A$5:$A$104,Ajustes!$D$5:$D$104,""),IF(_xlpm.x="",L115,_xlpm.x)) -> 32324 | D115: =C115*1.4 -> 45253.6 | E115: =D115-C115 -> 12929.6 | F115: 3 | G115: =D115*0.95 -> 42990.92 | H115: =D115*1.21 -> 54756.856 | J115: =C115*F115 -> 96972 | K115: =E115*F115 -> 38788.8 | L115: 32324 | M115: 2
A116: B-3065-FU | B116: DEFLEC.CAPOT FIAT TORO 22+ | C116: 53203 | D116: =C116*1.4 -> 74484.2 | E116: =D116-C116 -> 21281.2 | F116: 1 | G116: =D116*0.95 -> 70759.99 | H116: =D116*1.21 -> 90125.882
A117: B-1318-A | B117: DEFLEC.VENTANILLA FORD RANGER 12+ (JGO.DELANT.ADHESIVO) | C117: 37878 | D117: =C117*1.4 -> 53029.2 | E117: =D117-C117 -> 15151.2 | F117: 1 | G117: =D117*0.95 -> 50377.74 | H117: =D117*1.21 -> 64165.332
A118: B-1318-TA | B118: DEFLEC.VENTANILLA FORD RANGER 12+ (JGO.TRAS.ADHESIVO) | C118: 34975 | D118: =C118*1.4 -> 48965 | E118: =D118-C118 -> 13990 | F118: 1 | G118: =D118*0.95 -> 46516.75 | H118: =D118*1.21 -> 59247.65
A119: K-37 | B119: ENCHUFE PLASTICO P/LUZ TRAILER HEMBRA | C119: =_xlfn.LET(_xlpm.x,_xlfn.XLOOKUP(ROW(),Ajustes!$A$5:$A$104,Ajustes!$D$5:$D$104,""),IF(_xlpm.x="",L119,_xlpm.x)) -> 37389 | D119: =C119*1.4 -> 52344.6 | E119: =D119-C119 -> 14955.6 | F119: =_xlfn.LET(_xlpm.x,_xlfn.XLOOKUP(ROW(),Ajustes!$A$5:$A$104,Ajustes!$E$5:$E$104,""),IF(_xlpm.x="",M119,_xlpm.x)) -> 2 | G119: =D119*0.95 -> 49727.37 | H119: =D119*1.21 -> 63336.966 | J119: =C119*F119 -> 74778 | K119: =E119*F119 -> 29911.2 | L119: 37389 | M119: 2
A120: K-36 | B120: ENCHUFE PLASTICO P/LUZ TRAILER MACHO | C120: =_xlfn.LET(_xlpm.x,_xlfn.XLOOKUP(ROW(),Ajustes!$A$5:$A$104,Ajustes!$D$5:$D$104,""),IF(_xlpm.x="",L120,_xlpm.x)) -> 19522 | D120: =C120*1.4 -> 27330.8 | E120: =D120-C120 -> 7808.8 | F120: =_xlfn.LET(_xlpm.x,_xlfn.XLOOKUP(ROW(),Ajustes!$A$5:$A$104,Ajustes!$E$5:$E$104,""),IF(_xlpm.x="",M120,_xlpm.x)) -> 2 | G120: =D120*0.95 -> 25964.26 | H120: =D120*1.21 -> 33070.268 | J120: =C120*F120 -> 39044 | K120: =E120*F120 -> 15617.6 | L120: 19522 | M120: 2
A121: EFP-308 | B121: ENGANCHE CHEV.S-10 12+ C/PERNO "MAXITRACC" | C121: =_xlfn.LET(_xlpm.x,_xlfn.XLOOKUP(ROW(),Ajustes!$A$5:$A$104,Ajustes!$D$5:$D$104,""),IF(_xlpm.x="",L121,_xlpm.x)) -> 252201 | D121: =C121*1.4 -> 353081.4 | E121: =D121-C121 -> 100880.4 | F121: 2 | G121: =D121*0.95 -> 335427.33 | H121: =D121*1.21 -> 427228.49 | J121: =C121*F121 -> 504402 | K121: =E121*F121 -> 201760.8 | L121: 252201 | M121: 0
...

Sheet FILTROS
A2: BUSCAR =
A3: {=IF(B1="","",_xlfn.LET(_xlpm.coincide,_xlfn.LAMBDA(_xlpm.t,_xlpm.p,OR(ISNUMBER(SEARCH(_xlpm.t,_xlpm.p)),OR(_xlfn.MAP(_xlfn.SEQUENCE(LEN(_xlpm.t)+1,,0),_xlfn.LAMBDA(_xlpm.k,ISNUMBER(SEARCH(LEFT(_xlpm.t,_xlpm.k)&"?"&MID(_xlpm.t,_xlpm.k+1,LEN(_xlpm.t)),_xlpm.p))))),OR(_xlfn.MAP(_xlfn.SEQUENCE(LEN(_xlpm.t)),_xlfn.LAMBDA(_xlpm.k,ISNUMBER(SEARCH(REPLACE(_xlpm.t,_xlpm.k,1,"?"),_xlpm.p))))),IF(LEN(_xlpm.t)>3,OR(_xlfn.MAP(_xlfn.SEQUENCE(LEN(_xlpm.t)),_xlfn.LAMBDA(_xlpm.k,ISNUMBER(SEARCH(REPLACE(_xlpm.t,_xlpm.k,1,""),_xlpm.p))))),FALSE))),_xlpm.terminos,_xlfn.TOCOL(_xlfn.TEXTSPLIT(LOWER(TRIM(B1))," "),1),_xlpm.productos,LOWER($B$27:$B$884),_xlpm.puntaje,_xlfn.BYROW(_xlpm.productos,_xlfn.LAMBDA(_xlpm.p,SUM(_xlfn.MAP(_xlpm.terminos,_xlfn.LAMBDA(_xlpm.t,--_xlpm.coincide(_xlpm.t,_xlpm.p)))))),_xlpm.datos,_xlfn.HSTACK($A$27:$H$884,ROW($B$27:$B$884)),IFERROR(_xlfn.TAKE(_xlfn._xlws.FILTER(_xlpm.datos,(_xlpm.puntaje=ROWS(_xlpm.terminos))*($B$27:$B$884<>"")),20),"NO ENCONTRADO")))}
A4: CODIGO | B4: PRODUCTO | C4: FABRICA | D4: PUBLICO | E4: GANANCIA | F4: STOCK | G4: DESC. 5 % | H4: IVA 21 %
A5: 3165141146950 | B5: FILTRO DE NAFTA BOSCH MOTOS HONDA BIZ CG YAMAHA CRIPTON ZANELLA | C5: 4472 | D5: =C5*1.4 -> 6260.8 | E5: =D5-C5 -> 1788.8 | F5: 20 | G5: =D5*0.95 -> 5947.76 | H5: =D5*1.21 -> 7575.568
A6: 7799076006254 | B6: KIT FILTROS VOLSKWAGEN SURAN/FOX 1,6 MSI (15/25) | D6: =C6*1.4 -> 0 | E6: =D6-C6 -> 0 | F6: 14 | G6: =D6*0.95 -> 0 | H6: =D6*1.21 -> 0
A7: 7798186475806 | B7: KIT FILTROS VOLSKWAGEN SURAN/FOX/GOL TREND/VOYAGE 1,6 8V | D7: =C7*1.4 -> 0 | E7: =D7-C7 -> 0 | F7: 10 | G7: =D7*0.95 -> 0 | H7: =D7*1.21 -> 0
A8: 7799076010442 | B8: KIT FILTROS VOLSKWAGEN POLO/VIRTUS/TCROSS 1,6 MSI 117 Cv(17/18) | D8: =C8*1.4 -> 0 | E8: =D8-C8 -> 0 | F8: 6 | G8: =D8*0.95 -> 0 | H8: =D8*1.21 -> 0
A9: 7799076004564 | B9: KIT FILTROS VOLSKGAWEN GOL 1,6 8V 1997+ | D9: =C9*1.4 -> 0 | E9: =D9-C9 -> 0 | F9: 1 | G9: =D9*0.95 -> 0 | H9: =D9*1.21 -> 0
A10: 171174073318 | B10: KIT FILTROS VOLSKGAWEN SURAN/GOL/FOX/SAVEIRO 1,6 8V | D10: =C10*1.4 -> 0 | E10: =D10-C10 -> 0 | F10: 1 | G10: =D10*0.95 -> 0 | H10: =D10*1.21 -> 0
A11: 7798186477152 | B11: KIT FILTROS VOLSKWAGEN VENTO 2.5 2006 + | D11: =C11*1.4 -> 0 | E11: =D11-C11 -> 0 | F11: 4 | G11: =D11*0.95 -> 0 | H11: =D11*1.21 -> 0
A12: 7799076004014 | B12: KIT FILTROS VOLSKWAGEN UP! 1,0 75 CV MPI | D12: =C12*1.4 -> 0 | E12: =D12-C12 -> 0 | F12: 14 | G12: =D12*0.95 -> 0 | H12: =D12*1.21 -> 0
A13: 7799076005691 | B13: KIT FILTROS NISSAN FRONTIER NACIONAL 2018 + | D13: =C13*1.4 -> 0 | E13: =D13-C13 -> 0 | F13: 5 | G13: =D13*0.95 -> 0 | H13: =D13*1.21 -> 0
A14: 7798186479538 | B14: KIT FILTROS FIAT PALIO/SIENA/IDEA/SATRADA 1,6 ETORQ 2011+ | D14: =C14*1.4 -> 0 | E14: =D14-C14 -> 0 | F14: 2 | G14: =D14*0.95 -> 0 | H14: =D14*1.21 -> 0
A15: 7798186479347 | B15: KIT FILTROS FIAT TORO 2,0 16 V MULTIJET 2016+ | D15: =C15*1.4 -> 0 | E15: =D15-C15 -> 0 | F15: 7 | G15: =D15*0.95 -> 0 | H15: =D15*1.21 -> 0
A16: 7799076003345 | B16: KIT FILTROS JEEP RENEGADE/FIAT TORO NAFTA 1,8 16V 2016 + | D16: =C16*1.4 -> 0 | E16: =D16-C16 -> 0 | F16: 2 | G16: =D16*0.95 -> 0 | H16: =D16*1.21 -> 0
A17: 7798186475776 | B17: KIT FILTROS FIAT UNO WAY | D17: =C17*1.4 -> 0 | E17: =D17-C17 -> 0 | F17: 2 | G17: =D17*0.95 -> 0 | H17: =D17*1.21 -> 0
... A77: 171174073542 | B77: KIT FILTROS CHEVROLET S10 2.4 2.5 2.8 DURAMAS MWM 12+ | D77: =C77*1.4 -> 0 | E77: =D77-C77 -> 0 | F77: 7 | G77: =D77*0.95 -> 0 | H77: =D77*1.21 -> 0
D78: =C78*1.4 -> 0 | E78: =D78-C78 -> 0 | G78: =D78*0.95 -> 0 | H78: =D78*1.21 -> 0
D79: =C79*1.4 -> 0 | E79: =D79-C79 -> 0 | G79: =D79*0.95 -> 0 | H79: =D79*1.21 -> 0
D80: =C80*1.4 -> 0 | E80: =D80-C80 -> 0 | G80: =D80*0.95 -> 0 | H80: =D80*1.21 -> 0
D81: =C81*1.4 -> 0 | E81: =D81-C81 -> 0 | G81: =D81*0.95 -> 0 | H81: =D81*1.21 -> 0
D82: =C82*1.4 -> 0 | E82: =D82-C82 -> 0 | G82: =D82*0.95 -> 0 | H82: =D82*1.21 -> 0
D83: =C83*1.4 -> 0 | E83: =D83-C83 -> 0 | G83: =D83*0.95 -> 0 | H83: =D83*1.21 -> 0
D84: =C84*1.4 -> 0 | E84: =D84-C84 -> 0 | G84: =D84*0.95 -> 0 | H84: =D84*1.21 -> 0
D85: =C85*1.4 -> 0 | E85: =D85-C85 -> 0 | G85: =D85*0.95 -> 0 | H85: =D85*1.21 -> 0
D86: =C86*1.4 -> 0 | E86: =D86-C86 -> 0 | G86: =D86*0.95 -> 0 | H86: =D86*1.21 -> 0
D87: =C87*1.4 -> 0 | E87: =D87-C87 -> 0 | G87: =D87*0.95 -> 0 | H87: =D87*1.21 -> 0
D88: =C88*1.4 -> 0 | E88: =D88-C88 -> 0 | G88: =D88*0.95 -> 0 | H88: =D88*1.21 -> 0
D89: =C89*1.4 -> 0 | E89: =D89-C89 -> 0 | G89: =D89*0.95 -> 0 | H89: =D89*1.21 -> 0
... D490: =C490*1.4 -> 0 | E490: =D490-C490 -> 0 | G490: =D490*0.95 -> 0 | H490: =D490*1.21 -> 0
D491: =C491*1.4 -> 0 | E491: =D491-C491 -> 0 | G491: =D491*0.95 -> 0 | H491: =D491*1.21 -> 0 | I491: =D490*F490 -> 0
D492: =C492*1.4 -> 0 | E492: =D492-C492 -> 0 | G492: =D492*0.95 -> 0 | H492: =D492*1.21 -> 0 | I492: =D491*F491 -> 0
D493: =C493*1.4 -> 0 | E493: =D493-C493 -> 0 | G493: =D493*0.95 -> 0 | H493: =D493*1.21 -> 0 | I493: =D492*F492 -> 0
D494: =C494*1.4 -> 0 | E494: =D494-C494 -> 0 | G494: =D494*0.95 -> 0 | H494: =D494*1.21 -> 0 | I494: =D493*F493 -> 0
D495: =C495*1.4 -> 0 | E495: =D495-C495 -> 0 | G495: =D495*0.95 -> 0 | H495: =D495*1.21 -> 0 | I495: =D494*F494 -> 0
D496: =C496*1.4 -> 0 | E496: =D496-C496 -> 0 | G496: =D496*0.95 -> 0 | H496: =D496*1.21 -> 0 | I496: =D495*F495 -> 0
D497: =C497*1.4 -> 0 | E497: =D497-C497 -> 0 | G497: =D497*0.95 -> 0 | H497: =D497*1.21 -> 0 | I497: =D496*F496 -> 0
D498: =C498*1.4 -> 0 | E498: =D498-C498 -> 0 | G498: =D498*0.95 -> 0 | H498: =D498*1.21 -> 0 | I498: =D497*F497 -> 0
D499: =C499*1.4 -> 0 | E499: =D499-C499 -> 0 | G499: =D499*0.95 -> 0 | H499: =D499*1.21 -> 0 | I499: =D498*F498 -> 0
D500: =C500*1.4 -> 0 | E500: =D500-C500 -> 0 | G500: =D500*0.95 -> 0 | H500: =D500*1.21 -> 0 | I500: =D499*F499 -> 0
D501: =C501*1.4 -> 0 | E501: =D501-C501 -> 0 | G501: =D501*0.95 -> 0 | H501: =D501*1.21 -> 0 | I501: =D500*F500 -> 0
D502: =C502*1.4 -> 0 | E502: =D502-C502 -> 0 | G502: =D502*0.95 -> 0 | H502: =D502*1.21 -> 0 | I502: =D501*F501 -> 0
... D853: =C853*1.4 -> 0 | E853: =D853-C853 -> 0 | G853: =D853*0.95 -> 0 | H853: =D853*1.21 -> 0 | I853: =D852*F852 -> 0
I854: =D853*F853 -> 0
I855: =D854*F854 -> 0

Sheet norte
A1: {=_xlfn._xlws.FILTER(A5:H141,ISNUMBER(SEARCH(B2,A5:A141)))} -> #VALUE!
A2: BUSCAR =
A4: CODIGO | B4: PRODUCTO | C4: FABRICA | D4: PUBLICO | E4: GANANCIA | F4: STOCK | G4: DESC. 5 % | H4: IVA 21 %
A5: 7794004953938 | B5: CINTA AISLADORA | C5: 1704 | D5: =C5*1.4 -> 2385.6 | E5: =D5-C5 -> 681.6 | F5: 10 | G5: =D5*0.95 -> 2266.32 | H5: =D5*1.21 -> 2886.576
A6: 7792993001616 | B6: CABLE PUENTE 120 AMP 2,3 MTS | C6: 8973 | D6: =C6*1.4 -> 12562.2 | E6: =D6-C6 -> 3589.2 | F6: 2 | G6: =D6*0.95 -> 11934.09 | H6: =D6*1.21 -> 15200.262
A7: 17798090229967 | B7: LAVAPARABRISAS CONCENTRADO | C7: 1830 | D7: =C7*1.4 -> 2562 | E7: =D7-C7 -> 732 | F7: 24 | G7: =D7*0.95 -> 2433.9 | H7: =D7*1.21 -> 3100.02
A8: 7799064056407 | B8: CALCOS REGLAMENTARIAS | C8: 8094 | D8: =C8*1.4 -> 11331.6 | E8: =D8-C8 -> 3237.6 | F8: 6 | G8: =D8*0.95 -> 10765.02 | H8: =D8*1.21 -> 13711.236
A9: 7799064056469 | B9: CINTA REGLAMENTARIA X 1M INTERNACIONAL | C9: 5706 | D9: =C9*1.4 -> 7988.4 | E9: =D9-C9 -> 2282.4 | F9: 1 | G9: =D9*0.95 -> 7588.98 | H9: =D9*1.21 -> 9665.964
A10: 7799064056445 | B10: CINTA REGLAMENTARIA X 0,5 CEBRADA | C10: 4734 | D10: =C10*1.4 -> 6627.6 | E10: =D10-C10 -> 1893.6 | F10: 1 | G10: =D10*0.95 -> 6296.22 | H10: =D10*1.21 -> 8019.396
A11: 7794287000015 | B11: MATAFUEGO MELISAM POLVO 1 KILO | C11: 35117 | D11: =C11*1.4 -> 49163.8 | E11: =D11-C11 -> 14046.8 | F11: 2 | G11: =D11*0.95 -> 46705.61 | H11: =D11*1.21 -> 59488.198
A12: 7798090227119 | B12: INFLA Y SELLA FIXIT | C12: 13375 | D12: =C12*1.4 -> 18725 | E12: =D12-C12 -> 5350 | F12: 6 | G12: =D12*0.95 -> 17788.75 | H12: =D12*1.21 -> 22657.25
A13: 7798090220318 | B13: LIQUIDO DE FRENO WANDER TIPO 3 200CC | C13: 2993 | D13: =C13*1.4 -> 4190.2 | E13: =D13-C13 -> 1197.2 | F13: 24 | G13: =D13*0.95 -> 3980.69 | H13: =D13*1.21 -> 5070.142
A14: 7798121761193 | B14: BOTIQUIN PRIMEROS AUXILIOS | C14: 8489 | D14: =C14*1.4 -> 11884.6 | E14: =D14-C14 -> 3395.6 | F14: 2 | G14: =D14*0.95 -> 11290.37 | H14: =D14*1.21 -> 14380.366
A15: 7798090220035 | B15: AGUA DESMINERALIZADA X 5 LITROS | C15: 3057 | D15: =C15*1.4 -> 4279.8 | E15: =D15-C15 -> 1222.8 | F15: 24 | G15: =D15*0.95 -> 4065.81 | H15: =D15*1.21 -> 5178.558
A16: 7798058467601 | B16: ARRANCA MOTORES LOCX | C16: 12316 | D16: =C16*1.4 -> 17242.4 | E16: =D16-C16 -> 4926.4 | F16: 19 | G16: =D16*0.95 -> 16380.28 | H16: =D16*1.21 -> 20863.304
... A23: 267 | B23: CRIQUET HIDRAULICO CARRITO 2T | C23: 53766 | D23: =C23*1.4 -> 75272.4 | E23: =D23-C23 -> 21506.4 | F23: 1 | G23: =D23*0.95 -> 71508.78 | H23: =D23*1.21 -> 91079.604
D24: =C24*1.4 -> 0 | E24: =D24-C24 -> 0 | G24: =D24*0.95 -> 0 | H24: =D24*1.21 -> 0
D25: =C25*1.4 -> 0 | E25: =D25-C25 -> 0 | G25: =D25*0.95 -> 0 | H25: =D25*1.21 -> 0
D26: =C26*1.4 -> 0 | E26: =D26-C26 -> 0 | G26: =D26*0.95 -> 0 | H26: =D26*1.21 -> 0
D27: =C27*1.4 -> 0 | E27: =D27-C27 -> 0 | G27: =D27*0.95 -> 0 | H27: =D27*1.21 -> 0
D28: =C28*1.4 -> 0 | E28: =D28-C28 -> 0 | G28: =D28*0.95 -> 0 | H28: =D28*1.21 -> 0
D29: =C29*1.4 -> 0 | E29: =D29-C29 -> 0 | G29: =D29*0.95 -> 0 | H29: =D29*1.21 -> 0
D30: =C30*1.4 -> 0 | E30: =D30-C30 -> 0 | G30: =D30*0.95 -> 0 | H30: =D30*1.21 -> 0
D31: =C31*1.4 -> 0 | E31: =D31-C31 -> 0 | G31: =D31*0.95 -> 0 | H31: =D31*1.21 -> 0
D32: =C32*1.4 -> 0 | E32: =D32-C32 -> 0 | G32: =D32*0.95 -> 0 | H32: =D32*1.21 -> 0
D33: =C33*1.4 -> 0 | E33: =D33-C33 -> 0 | G33: =D33*0.95 -> 0 | H33: =D33*1.21 -> 0
D34: =C34*1.4 -> 0 | E34: =D34-C34 -> 0 | G34: =D34*0.95 -> 0 | H34: =D34*1.21 -> 0
D35: =C35*1.4 -> 0 | E35: =D35-C35 -> 0 | G35: =D35*0.95 -> 0 | H35: =D35*1.21 -> 0
... D495: =C495*1.4 -> 0 | E495: =D495-C495 -> 0 | G495: =D495*0.95 -> 0 | H495: =D495*1.21 -> 0
D496: =C496*1.4 -> 0 | E496: =D496-C496 -> 0 | G496: =D496*0.95 -> 0 | H496: =D496*1.21 -> 0 | I496: =D495*F495 -> 0
D497: =C497*1.4 -> 0 | E497: =D497-C497 -> 0 | G497: =D497*0.95 -> 0 | H497: =D497*1.21 -> 0 | I497: =D496*F496 -> 0
D498: =C498*1.4 -> 0 | E498: =D498-C498 -> 0 | G498: =D498*0.95 -> 0 | H498: =D498*1.21 -> 0 | I498: =D497*F497 -> 0
D499: =C499*1.4 -> 0 | E499: =D499-C499 -> 0 | G499: =D499*0.95 -> 0 | H499: =D499*1.21 -> 0 | I499: =D498*F498 -> 0
D500: =C500*1.4 -> 0 | E500: =D500-C500 -> 0 | G500: =D500*0.95 -> 0 | H500: =D500*1.21 -> 0 | I500: =D499*F499 -> 0
D501: =C501*1.4 -> 0 | E501: =D501-C501 -> 0 | G501: =D501*0.95 -> 0 | H501: =D501*1.21 -> 0 | I501: =D500*F500 -> 0
D502: =C502*1.4 -> 0 | E502: =D502-C502 -> 0 | G502: =D502*0.95 -> 0 | H502: =D502*1.21 -> 0 | I502: =D501*F501 -> 0
D503: =C503*1.4 -> 0 | E503: =D503-C503 -> 0 | G503: =D503*0.95 -> 0 | H503: =D503*1.21 -> 0 | I503: =D502*F502 -> 0
D504: =C504*1.4 -> 0 | E504: =D504-C504 -> 0 | G504: =D504*0.95 -> 0 | H504: =D504*1.21 -> 0 | I504: =D503*F503 -> 0
D505: =C505*1.4 -> 0 | E505: =D505-C505 -> 0 | G505: =D505*0.95 -> 0 | H505: =D505*1.21 -> 0 | I505: =D504*F504 -> 0
D506: =C506*1.4 -> 0 | E506: =D506-C506 -> 0 | G506: =D506*0.95 -> 0 | H506: =D506*1.21 -> 0 | I506: =D505*F505 -> 0
D507: =C507*1.4 -> 0 | E507: =D507-C507 -> 0 | G507: =D507*0.95 -> 0 | H507: =D507*1.21 -> 0 | I507: =D506*F506 -> 0
... D858: =C858*1.4 -> 0 | E858: =D858-C858 -> 0 | G858: =D858*0.95 -> 0 | H858: =D858*1.21 -> 0 | I858: =D857*F857 -> 0
I859: =D858*F858 -> 0
I860: =D859*F859 -> 0

Sheet big toys
A1: {=_xlfn._xlws.FILTER(A5:H145,ISNUMBER(SEARCH(B2,A5:A145)))} -> #VALUE!
A2: BUSCAR =
E3: Precios con iva venta al publico
A4: CODIGO | B4: PRODUCTO | C4: FABRICA | D4: PUBLICO | E4: GANANCIA | F4: STOCK | G4: DESC. 5 % | H4: IVA 21 %
A5: LTG-AM-001 | B5: AMORTIGUADOR PORTON AMAROK | C5: 63750 | D5: =C5*1.4 -> 89250 | E5: =D5-C5 -> 25500 | F5: 2 | G5: =D5*0.95 -> 84787.5 | H5: =D5*1.21 -> 107992.5
A6: LSPR-001 | B6: AMORTIGUADOR CAPOT HILUX/ SW4 2016-2022 | C6: 73440 | D6: =C6*1.4 -> 102816 | E6: =D6-C6 -> 29376 | F6: 1 | G6: =D6*0.95 -> 97675.2 | H6: =D6*1.21 -> 124407.36
A7: LTY-025-EXT | B7: SENSOR PRESION NEUMATICO DIGITAL | C7: 60480 | D7: =C7*1.4 -> 84672 | E7: =D7-C7 -> 24192 | F7: 3 | G7: =D7*0.95 -> 80438.4 | H7: =D7*1.21 -> 102453.12
A8: LPW-003 | B8: SOPORTES STARLINK P/ VIDRIO 4 VENTOSAS | C8: 45000 | D8: =C8*1.4 -> 63000 | E8: =D8-C8 -> 18000 | F8: 2 | G8: =D8*0.95 -> 59850 | H8: =D8*1.21 -> 76230
A9: RE21-013 | B9: FENDERS HILUX 2021 | C9: 297500 | D9: =C9*1.4 -> 416500 | E9: =D9-C9 -> 119000 | F9: 1 | G9: =D9*0.95 -> 395675 | H9: =D9*1.21 -> 503965
A10: LG-002 | B10: LUCES LED KIT X4 | C10: 15530 | D10: =C10*1.4 -> 21742 | E10: =D10-C10 -> 6212 | F10: 8 | G10: =D10*0.95 -> 20654.9 | H10: =D10*1.21 -> 26307.82
A11: LPS-010 | B11: SOPAPA VACIO 75MM DIAMETRO | C11: 50490 | D11: =C11*1.4 -> 70686 | E11: =D11-C11 -> 20196 | F11: 2 | G11: =D11*0.95 -> 67151.7 | H11: =D11*1.21 -> 85530.06
A12: 6W037 | B12: SEPARADOR RUEDA BTX HILUX/ SW4/ DAKOTA/ TITANO 6X139 32MM | C12: 53192 | D12: =C12*1.4 -> 74468.8 | E12: =D12-C12 -> 21276.8 | F12: 4 | G12: =D12*0.95 -> 70745.36 | H12: =D12*1.21 -> 90107.248
A13: 5W074 | B13: SEPARADOR RUEDA BTX AMAROK 5X120 38MM X UNIDAD | C13: 51229 | D13: =C13*1.4 -> 71720.6 | E13: =D13-C13 -> 20491.6 | F13: 8 | G13: =D13*0.95 -> 68134.57 | H13: =D13*1.21 -> 86781.926
A14: IV001 | B14: INVERTER 500W | C14: 55539 | D14: =C14*1.4 -> 77754.6 | E14: =D14-C14 -> 22215.6 | F14: 1 | G14: =D14*0.95 -> 73866.87 | H14: =D14*1.21 -> 94083.066
A15: 15361+LPS-011 | B15: SOPORTES ANT. STARLINK (CASE) +4 BASE IMANTADA 80MM DIAM. | C15: 146913 | D15: =C15*1.4 -> 205678.2 | E15: =D15-C15 -> 58765.2 | F15: 3 | G15: =D15*0.95 -> 195394.29 | H15: =D15*1.21 -> 248870.62
A16: 15361 | B16: SOPORTES ANTENA STARLINK (CASE) | C16: 84793 | D16: =C16*1.4 -> 118710.2 | E16: =D16-C16 -> 33917.2 | F16: 3 | G16: =D16*0.95 -> 112774.69 | H16: =D16*1.21 -> 143639.34
A17: LPS-011 | B17: BASE IMANTADA 80MM DIAMETRO X UNIDAD | C17: 15530 | D17: =C17*1.4 -> 21742 | E17: =D17-C17 -> 6212 | F17: 12 | G17: =D17*0.95 -> 20654.9 | H17: =D17*1.21 -> 26307.82
A18: 6W053 | B18: SEPARADOR DE RUEDAS RANGER 6X139 38MM | C18: 54763 | D18: =C18*1.4 -> 76668.2 | E18: =D18-C18 -> 21905.2 | F18: 4 | G18: =D18*0.95 -> 72834.79 | H18: =D18*1.21 -> 92768.522
A19: L9 | B19: AMORTIGUADOR DE PORTON RANGER 23+ | C19: 72710 | D19: =C19*1.4 -> 101794 | E19: =D19-C19 -> 29084 | F19: 1 | G19: =D19*0.95 -> 96704.3 | H19: =D19*1.21 -> 123170.74
B20: STARLINK | C20: 180000 | D20: =C20*1.4 -> 252000 | E20: =D20-C20 -> 72000 | F20: 3 | G20: =D20*0.95 -> 239400 | H20: =D20*1.21 -> 304920
D21: =C21*1.4 -> 0 | E21: =D21-C21 -> 0 | G21: =D21*0.95 -> 0 | H21: =D21*1.21 -> 0
D22: =C22*1.4 -> 0 | E22: =D22-C22 -> 0 | G22: =D22*0.95 -> 0 | H22: =D22*1.21 -> 0
D23: =C23*1.4 -> 0 | E23: =D23-C23 -> 0 | G23: =D23*0.95 -> 0 | H23: =D23*1.21 -> 0
D24: =C24*1.4 -> 0 | E24: =D24-C24 -> 0 | G24: =D24*0.95 -> 0 | H24: =D24*1.21 -> 0
D25: =C25*1.4 -> 0 | E25: =D25-C25 -> 0 | G25: =D25*0.95 -> 0 | H25: =D25*1.21 -> 0
D26: =C26*1.4 -> 0 | E26: =D26-C26 -> 0 | G26: =D26*0.95 -> 0 | H26: =D26*1.21 -> 0
D27: =C27*1.4 -> 0 | E27: =D27-C27 -> 0 | G27: =D27*0.95 -> 0 | H27: =D27*1.21 -> 0
D28: =C28*1.4 -> 0 | E28: =D28-C28 -> 0 | G28: =D28*0.95 -> 0 | H28: =D28*1.21 -> 0
D29: =C29*1.4 -> 0 | E29: =D29-C29 -> 0 | G29: =D29*0.95 -> 0 | H29: =D29*1.21 -> 0
D30: =C30*1.4 -> 0 | E30: =D30-C30 -> 0 | G30: =D30*0.95 -> 0 | H30: =D30*1.21 -> 0
D31: =C31*1.4 -> 0 | E31: =D31-C31 -> 0 | G31: =D31*0.95 -> 0 | H31: =D31*1.21 -> 0
D32: =C32*1.4 -> 0 | E32: =D32-C32 -> 0 | G32: =D32*0.95 -> 0 | H32: =D32*1.21 -> 0
... D494: =C494*1.4 -> 0 | E494: =D494-C494 -> 0 | G494: =D494*0.95 -> 0 | H494: =D494*1.21 -> 0
D495: =C495*1.4 -> 0 | E495: =D495-C495 -> 0 | G495: =D495*0.95 -> 0 | H495: =D495*1.21 -> 0 | I495: =D494*F494 -> 0
D496: =C496*1.4 -> 0 | E496: =D496-C496 -> 0 | G496: =D496*0.95 -> 0 | H496: =D496*1.21 -> 0 | I496: =D495*F495 -> 0
D497: =C497*1.4 -> 0 | E497: =D497-C497 -> 0 | G497: =D497*0.95 -> 0 | H497: =D497*1.21 -> 0 | I497: =D496*F496 -> 0
D498: =C498*1.4 -> 0 | E498: =D498-C498 -> 0 | G498: =D498*0.95 -> 0 | H498: =D498*1.21 -> 0 | I498: =D497*F497 -> 0
D499: =C499*1.4 -> 0 | E499: =D499-C499 -> 0 | G499: =D499*0.95 -> 0 | H499: =D499*1.21 -> 0 | I499: =D498*F498 -> 0
D500: =C500*1.4 -> 0 | E500: =D500-C500 -> 0 | G500: =D500*0.95 -> 0 | H500: =D500*1.21 -> 0 | I500: =D499*F499 -> 0
D501: =C501*1.4 -> 0 | E501: =D501-C501 -> 0 | G501: =D501*0.95 -> 0 | H501: =D501*1.21 -> 0 | I501: =D500*F500 -> 0
D502: =C502*1.4 -> 0 | E502: =D502-C502 -> 0 | G502: =D502*0.95 -> 0 | H502: =D502*1.21 -> 0 | I502: =D501*F501 -> 0
D503: =C503*1.4 -> 0 | E503: =D503-C503 -> 0 | G503: =D503*0.95 -> 0 | H503: =D503*1.21 -> 0 | I503: =D502*F502 -> 0
D504: =C504*1.4 -> 0 | E504: =D504-C504 -> 0 | G504: =D504*0.95 -> 0 | H504: =D504*1.21 -> 0 | I504: =D503*F503 -> 0
D505: =C505*1.4 -> 0 | E505: =D505-C505 -> 0 | G505: =D505*0.95 -> 0 | H505: =D505*1.21 -> 0 | I505: =D504*F504 -> 0
D506: =C506*1.4 -> 0 | E506: =D506-C506 -> 0 | G506: =D506*0.95 -> 0 | H506: =D506*1.21 -> 0 | I506: =D505*F505 -> 0
... D857: =C857*1.4 -> 0 | E857: =D857-C857 -> 0 | G857: =D857*0.95 -> 0 | H857: =D857*1.21 -> 0 | I857: =D856*F856 -> 0
I858: =D857*F857 -> 0
I859: =D858*F858 -> 0

Sheet Luces led
A1: {=_xlfn._xlws.FILTER(A5:H147,ISNUMBER(SEARCH(B2,A5:A147)))} -> #VALUE!
A2: BUSCAR =
A4: CODIGO | B4: PRODUCTO | C4: FABRICA | D4: PUBLICO | E4: GANANCIA | F4: STOCK | G4: DESC. 5 % | H4: IVA 21 %
A5: 661094211330 | B5: BARRA LED CURVA 180 WATTS BLANCA | C5: 60000 | E5: =D5-C5 -> -60000 | F5: 2 | G5: =D5*0.95 -> 0 | H5: =D5*1.21 -> 0
A6: 661094207463 | B6: BARRA LED CURVA 120 WATTS BLANCA | D6: =C6*1.4 -> 0 | E6: =D6-C6 -> 0 | G6: =D6*0.95 -> 0 | H6: =D6*1.21 -> 0
A7: 661094211286 | B7: BARRA LED RECTA 180 WATTS BLANCA | C7: 60000 | D7: =C7*1.4 -> 84000 | E7: =D7-C7 -> 24000 | F7: 2 | G7: =D7*0.95 -> 79800 | H7: =D7*1.21 -> 101640
B8: SNORKEL FORD RANGER | C8: 140000 | D8: =C8*1.4 -> 196000 | E8: =D8-C8 -> 56000 | F8: 2 | G8: =D8*0.95 -> 186200 | H8: =D8*1.21 -> 237160
B9: SNORKEL TOYOTA HILUX | C9: 140000 | D9: =C9*1.4 -> 196000 | E9: =D9-C9 -> 56000 | F9: 1 | G9: =D9*0.95 -> 186200 | H9: =D9*1.21 -> 237160
A10: 661094210913 | B10: BARRA LED RECTA 120 WATTS 52 CM | C10: 51000 | D10: =C10*1.4 -> 71400 | E10: =D10-C10 -> 20400 | F10: 1 | G10: =D10*0.95 -> 67830 | H10: =D10*1.21 -> 86394
A11: 661094207463 | B11: BARRA LED CURVA 120 WATTS BLANCA 52 CM | C11: 51000 | D11: =C11*1.4 -> 71400 | E11: =D11-C11 -> 20400 | F11: 1 | G11: =D11*0.95 -> 67830 | H11: =D11*1.21 -> 86394
A12: 661094222473 | B12: FARO LED REDONDO 12V 96 WATTS | C12: 15000 | D12: =C12*1.4 -> 21000 | E12: =D12-C12 -> 6000 | F12: 4 | G12: =D12*0.95 -> 19950 | H12: =D12*1.21 -> 25410
A13: 661094206961 | B13: FARO LED REDONDO 9V 27 WATTS | C13: 10000 | D13: =C13*1.4 -> 14000 | E13: =D13-C13 -> 4000 | F13: 3 | G13: =D13*0.95 -> 13300 | H13: =D13*1.21 -> 16940
B14: BARRA LED CUADRADA CHICA | C14: 20000 | D14: =C14*1.4 -> 28000 | E14: =D14-C14 -> 8000 | F14: 3 | G14: =D14*0.95 -> 26600 | H14: =D14*1.21 -> 33880
A15: 661094216533 | B15: Kit Cree Led H15 Canbus Alta Diurna Ranger/amarok V6/cruze | C15: 85000 | D15: =C15*1.4 -> 119000 | E15: =D15-C15 -> 34000 | F15: 3 | G15: =D15*0.95 -> 113050 | H15: =D15*1.21 -> 143990
A16: 661094212184 | B16: Kit Cree Led H4 S6 Pesados 22000lm 24v Heavy Duty Camiones | C16: 22000 | D16: =C16*1.4 -> 30800 | E16: =D16-C16 -> 8800 | F16: 7 | G16: =D16*0.95 -> 29260 | H16: =D16*1.21 -> 37268
A17: 661094215512 | B17: Kit Cree Led C6 Mini 12v H11 | C17: 8000 | D17: =C17*1.4 -> 11200 | E17: =D17-C17 -> 3200 | F17: 6 | G17: =D17*0.95 -> 10640 | H17: =D17*1.21 -> 13552
A18: 661094215499 | B18: Kit Cree Led C6 Mini 12v H7 | C18: 8000 | D18: =C18*1.4 -> 11200 | E18: =D18-C18 -> 3200 | F18: 2 | G18: =D18*0.95 -> 10640 | H18: =D18*1.21 -> 13552
A19: 661094215505 | B19: Kit Cree Led C6 Mini 12v H1 | C19: 8000 | D19: =C19*1.4 -> 11200 | E19: =D19-C19 -> 3200 | F19: 4 | G19: =D19*0.95 -> 10640 | H19: =D19*1.21 -> 13552
A20: 661094215536 | B20: Kit Cree Led C6 Mini 12v H3 | C20: 8000 | D20: =C20*1.4 -> 11200 | E20: =D20-C20 -> 3200 | F20: 4 | G20: =D20*0.95 -> 10640 | H20: =D20*1.21 -> 13552
A21: 661094215581 | B21: Kit Cree Led C6 Mini 12v 9004 | C21: 8000 | D21: =C21*1.4 -> 11200 | E21: =D21-C21 -> 3200 | F21: 3 | G21: =D21*0.95 -> 10640 | H21: =D21*1.21 -> 13552
A22: 661094215482 | B22: Kit Cree Led C6 Mini 12v H4 | C22: 8000 | D22: =C22*1.4 -> 11200 | E22: =D22-C22 -> 3200 | F22: 0 | G22: =D22*0.95 -> 10640 | H22: =D22*1.21 -> 13552
A23: 661094215567 | B23: Kit Cree Led C6 Mini 12v 9005 | C23: 8000 | D23: =C23*1.4 -> 11200 | E23: =D23-C23 -> 3200 | F23: 5 | G23: =D23*0.95 -> 10640 | H23: =D23*1.21 -> 13552
A24: 661094215529 | B24: Kit Cree Led C6 Mini 12v 9006 | C24: 8000 | D24: =C24*1.4 -> 11200 | E24: =D24-C24 -> 3200 | F24: 7 | G24: =D24*0.95 -> 10640 | H24: =D24*1.21 -> 13552
A25: 661094215550 | B25: Kit Cree Led C6 Mini 12v H27 | C25: 16000 | D25: =C25*1.4 -> 22400 | E25: =D25-C25 -> 6400 | F25: 3 | G25: =D25*0.95 -> 21280 | H25: =D25*1.21 -> 27104
A26: 661094215543 | B26: Kit Cree Led C6 Mini 12v H16-PSX | C26: 18000 | D26: =C26*1.4 -> 25200 | E26: =D26-C26 -> 7200 | F26: 1 | G26: =D26*0.95 -> 23940 | H26: =D26*1.21 -> 30492
A27: 661094215543 | B27: Kit Cree Led C6 Mini 12v PSX24W | C27: 18000 | D27: =C27*1.4 -> 25200 | E27: =D27-C27 -> 7200 | F27: 2 | G27: =D27*0.95 -> 23940 | H27: =D27*1.21 -> 30492
B28: Cable 2 hilos x 1,5 mm ( por metro) | C28: 2760 | D28: =C28*1.4 -> 3864 | E28: =D28-C28 -> 1104 | G28: =D28*0.95 -> 3670.8 | H28: =D28*1.21 -> 4675.44
D29: =C29*1.4 -> 0 | E29: =D29-C29 -> 0 | G29: =D29*0.95 -> 0 | H29: =D29*1.21 -> 0
D30: =C30*1.4 -> 0 | E30: =D30-C30 -> 0 | G30: =D30*0.95 -> 0 | H30: =D30*1.21 -> 0
D31: =C31*1.4 -> 0 | E31: =D31-C31 -> 0 | G31: =D31*0.95 -> 0 | H31: =D31*1.21 -> 0
D32: =C32*1.4 -> 0 | E32: =D32-C32 -> 0 | G32: =D32*0.95 -> 0 | H32: =D32*1.21 -> 0
D33: =C33*1.4 -> 0 | E33: =D33-C33 -> 0 | G33: =D33*0.95 -> 0 | H33: =D33*1.21 -> 0
D34: =C34*1.4 -> 0 | E34: =D34-C34 -> 0 | G34: =D34*0.95 -> 0 | H34: =D34*1.21 -> 0
D35: =C35*1.4 -> 0 | E35: =D35-C35 -> 0 | G35: =D35*0.95 -> 0 | H35: =D35*1.21 -> 0
D36: =C36*1.4 -> 0 | E36: =D36-C36 -> 0 | G36: =D36*0.95 -> 0 | H36: =D36*1.21 -> 0
D37: =C37*1.4 -> 0 | E37: =D37-C37 -> 0 | G37: =D37*0.95 -> 0 | H37: =D37*1.21 -> 0
D38: =C38*1.4 -> 0 | E38: =D38-C38 -> 0 | G38: =D38*0.95 -> 0 | H38: =D38*1.21 -> 0
D39: =C39*1.4 -> 0 | E39: =D39-C39 -> 0 | G39: =D39*0.95 -> 0 | H39: =D39*1.21 -> 0
D40: =C40*1.4 -> 0 | E40: =D40-C40 -> 0 | G40: =D40*0.95 -> 0 | H40: =D40*1.21 -> 0
... D496: =C496*1.4 -> 0 | E496: =D496-C496 -> 0 | G496: =D496*0.95 -> 0 | H496: =D496*1.21 -> 0
D497: =C497*1.4 -> 0 | E497: =D497-C497 -> 0 | G497: =D497*0.95 -> 0 | H497: =D497*1.21 -> 0 | I497: =D496*F496 -> 0
D498: =C498*1.4 -> 0 | E498: =D498-C498 -> 0 | G498: =D498*0.95 -> 0 | H498: =D498*1.21 -> 0 | I498: =D497*F497 -> 0
D499: =C499*1.4 -> 0 | E499: =D499-C499 -> 0 | G499: =D499*0.95 -> 0 | H499: =D499*1.21 -> 0 | I499: =D498*F498 -> 0
D500: =C500*1.4 -> 0 | E500: =D500-C500 -> 0 | G500: =D500*0.95 -> 0 | H500: =D500*1.21 -> 0 | I500: =D499*F499 -> 0
D501: =C501*1.4 -> 0 | E501: =D501-C501 -> 0 | G501: =D501*0.95 -> 0 | H501: =D501*1.21 -> 0 | I501: =D500*F500 -> 0
D502: =C502*1.4 -> 0 | E502: =D502-C502 -> 0 | G502: =D502*0.95 -> 0 | H502: =D502*1.21 -> 0 | I502: =D501*F501 -> 0
D503: =C503*1.4 -> 0 | E503: =D503-C503 -> 0 | G503: =D503*0.95 -> 0 | H503: =D503*1.21 -> 0 | I503: =D502*F502 -> 0
D504: =C504*1.4 -> 0 | E504: =D504-C504 -> 0 | G504: =D504*0.95 -> 0 | H504: =D504*1.21 -> 0 | I504: =D503*F503 -> 0
D505: =C505*1.4 -> 0 | E505: =D505-C505 -> 0 | G505: =D505*0.95 -> 0 | H505: =D505*1.21 -> 0 | I505: =D504*F504 -> 0
D506: =C506*1.4 -> 0 | E506: =D506-C506 -> 0 | G506: =D506*0.95 -> 0 | H506: =D506*1.21 -> 0 | I506: =D505*F505 -> 0
D507: =C507*1.4 -> 0 | E507: =D507-C507 -> 0 | G507: =D507*0.95 -> 0 | H507: =D507*1.21 -> 0 | I507: =D506*F506 -> 0
D508: =C508*1.4 -> 0 | E508: =D508-C508 -> 0 | G508: =D508*0.95 -> 0 | H508: =D508*1.21 -> 0 | I508: =D507*F507 -> 0
... D859: =C859*1.4 -> 0 | E859: =D859-C859 -> 0 | G859: =D859*0.95 -> 0 | H859: =D859*1.21 -> 0 | I859: =D858*F858 -> 0
I860: =D859*F859 -> 0
I861: =D860*F860 -> 0

Sheet baterias
A1: {=_xlfn._xlws.FILTER(A5:H147,ISNUMBER(SEARCH(B2,A5:A147)))} -> #VALUE!
A2: BUSCAR =
B3: PRECIO CON LA ENTREGA DE LA USADA, SI NO SUMAR 5 %
A4: CODIGO | B4: PRODUCTO | C4: FABRICA | D4: PUBLICO | E4: GANANCIA | F4: STOCK | G4: DESC. 5 % | H4: IVA 21 %
A5: 02085MR200186 | B5: BATERIA GIAGNONI X 65 AMPER (AUTOS) | C5: 97 | D5: =C5*1.25 -> 121.25 | E5: =D5-C5 -> 24.25 | F5: 0 | G5: =D5*0.95 -> 115.1875 | H5: =D5*1.21 -> 146.7125
A6: 02022MR210278 | B6: BATERIA GIAGNONI X 65 AMPER REFORZADA (AUTOS) | C6: 112000 | D6: =C6*1.25 -> 140000 | E6: =D6-C6 -> 28000 | F6: 2 | G6: =D6*0.95 -> 133000 | H6: =D6*1.21 -> 169400
A7: 02068SE210166 | B7: BATERIA GIAGNONI 12 V X 110 AMPER "C" (PERKINS,CAMIONES) | C7: 200000 | D7: =C7*1.25 -> 250000 | E7: =D7-C7 -> 50000 | F7: 2 | G7: =D7*0.95 -> 237500 | H7: =D7*1.21 -> 302500
A8: 02035MR210150 | B8: BATERIA GIAGNONI 12 V X 110 AMPER "B" (AMAROK,S10,MERCEDEZ) | C8: 210000 | D8: =C8*1.25 -> 262500 | E8: =D8-C8 -> 52500 | F8: 2 | G8: =D8*0.95 -> 249375 | H8: =D8*1.21 -> 317625
A9: 01029MR341259 | B9: BATERIA GIAGNONI 12V X 90 AMPER "B" (RANGER,MASTER,F100) | C9: 170000 | D9: =C9*1.25 -> 212500 | E9: =D9-C9 -> 42500 | F9: 2 | G9: =D9*0.95 -> 201875 | H9: =D9*1.21 -> 257125
C10: 337684 | D10: =C10*1.25 -> 422105 | E10: =D10-C10 -> 84421 | G10: =D10*0.95 -> 400999.75 | H10: =D10*1.21 -> 510747.05
D11: =C11*1.25 -> 0 | E11: =D11-C11 -> 0 | G11: =D11*0.95 -> 0 | H11: =D11*1.21 -> 0
D12: =C12*1.25 -> 0 | E12: =D12-C12 -> 0 | G12: =D12*0.95 -> 0 | H12: =D12*1.21 -> 0
G13: =D13*0.95 -> 0 | H13: =D13*1.21 -> 0
D14: =C13*1.25 -> 0 | E14: =D14-C13 -> 0 | G14: =D14*0.95 -> 0 | H14: =D14*1.21 -> 0
D15: =C14*1.25 -> 0 | E15: =D15-C14 -> 0 | G15: =D15*0.95 -> 0 | H15: =D15*1.21 -> 0
D16: =C15*1.25 -> 0 | E16: =D16-C15 -> 0 | G16: =D16*0.95 -> 0 | H16: =D16*1.21 -> 0
D17: =C16*1.25 -> 0 | E17: =D17-C16 -> 0 | G17: =D17*0.95 -> 0 | H17: =D17*1.21 -> 0
D18: =C17*1.25 -> 0 | E18: =D18-C17 -> 0 | G18: =D18*0.95 -> 0 | H18: =D18*1.21 -> 0
D19: =C18*1.25 -> 0 | E19: =D19-C18 -> 0 | G19: =D19*0.95 -> 0 | H19: =D19*1.21 -> 0
D20: =C19*1.25 -> 0 | E20: =D20-C19 -> 0 | G20: =D20*0.95 -> 0 | H20: =D20*1.21 -> 0
D21: =C20*1.25 -> 0 | E21: =D21-C20 -> 0 | G21: =D21*0.95 -> 0 | H21: =D21*1.21 -> 0
D22: =C21*1.25 -> 0 | E22: =D22-C21 -> 0 | G22: =D22*0.95 -> 0 | H22: =D22*1.21 -> 0
D23: =C22*1.25 -> 0 | E23: =D23-C22 -> 0 | G23: =D23*0.95 -> 0 | H23: =D23*1.21 -> 0
D24: =C23*1.25 -> 0 | E24: =D24-C23 -> 0 | G24: =D24*0.95 -> 0 | H24: =D24*1.21 -> 0
D25: =C24*1.25 -> 0 | E25: =D25-C24 -> 0 | G25: =D25*0.95 -> 0 | H25: =D25*1.21 -> 0
D26: =C25*1.25 -> 0 | E26: =D26-C25 -> 0 | G26: =D26*0.95 -> 0 | H26: =D26*1.21 -> 0
E27: =D27-C26 -> 0 | G27: =D27*0.95 -> 0 | H27: =D27*1.21 -> 0
D28: =C28*1.25 -> 0 | E28: =D28-C28 -> 0 | G28: =D28*0.95 -> 0 | H28: =D28*1.21 -> 0
D29: =C29*1.4 -> 0 | E29: =D29-C29 -> 0 | G29: =D29*0.95 -> 0 | H29: =D29*1.21 -> 0
D30: =C30*1.4 -> 0 | E30: =D30-C30 -> 0 | G30: =D30*0.95 -> 0 | H30: =D30*1.21 -> 0
D31: =C31*1.4 -> 0 | E31: =D31-C31 -> 0 | G31: =D31*0.95 -> 0 | H31: =D31*1.21 -> 0
D32: =C32*1.4 -> 0 | E32: =D32-C32 -> 0 | G32: =D32*0.95 -> 0 | H32: =D32*1.21 -> 0
D33: =C33*1.4 -> 0 | E33: =D33-C33 -> 0 | G33: =D33*0.95 -> 0 | H33: =D33*1.21 -> 0
D34: =C34*1.4 -> 0 | E34: =D34-C34 -> 0 | G34: =D34*0.95 -> 0 | H34: =D34*1.21 -> 0
D35: =C35*1.4 -> 0 | E35: =D35-C35 -> 0 | G35: =D35*0.95 -> 0 | H35: =D35*1.21 -> 0
D36: =C36*1.4 -> 0 | E36: =D36-C36 -> 0 | G36: =D36*0.95 -> 0 | H36: =D36*1.21 -> 0
D37: =C37*1.4 -> 0 | E37: =D37-C37 -> 0 | G37: =D37*0.95 -> 0 | H37: =D37*1.21 -> 0
D38: =C38*1.4 -> 0 | E38: =D38-C38 -> 0 | G38: =D38*0.95 -> 0 | H38: =D38*1.21 -> 0
D39: =C39*1.4 -> 0 | E39: =D39-C39 -> 0 | G39: =D39*0.95 -> 0 | H39: =D39*1.21 -> 0
D40: =C40*1.4 -> 0 | E40: =D40-C40 -> 0 | G40: =D40*0.95 -> 0 | H40: =D40*1.21 -> 0
... D496: =C496*1.4 -> 0 | E496: =D496-C496 -> 0 | G496: =D496*0.95 -> 0 | H496: =D496*1.21 -> 0
D497: =C497*1.4 -> 0 | E497: =D497-C497 -> 0 | G497: =D497*0.95 -> 0 | H497: =D497*1.21 -> 0 | I497: =D496*F496 -> 0
D498: =C498*1.4 -> 0 | E498: =D498-C498 -> 0 | G498: =D498*0.95 -> 0 | H498: =D498*1.21 -> 0 | I498: =D497*F497 -> 0
D499: =C499*1.4 -> 0 | E499: =D499-C499 -> 0 | G499: =D499*0.95 -> 0 | H499: =D499*1.21 -> 0 | I499: =D498*F498 -> 0
D500: =C500*1.4 -> 0 | E500: =D500-C500 -> 0 | G500: =D500*0.95 -> 0 | H500: =D500*1.21 -> 0 | I500: =D499*F499 -> 0
D501: =C501*1.4 -> 0 | E501: =D501-C501 -> 0 | G501: =D501*0.95 -> 0 | H501: =D501*1.21 -> 0 | I501: =D500*F500 -> 0
D502: =C502*1.4 -> 0 | E502: =D502-C502 -> 0 | G502: =D502*0.95 -> 0 | H502: =D502*1.21 -> 0 | I502: =D501*F501 -> 0
D503: =C503*1.4 -> 0 | E503: =D503-C503 -> 0 | G503: =D503*0.95 -> 0 | H503: =D503*1.21 -> 0 | I503: =D502*F502 -> 0
D504: =C504*1.4 -> 0 | E504: =D504-C504 -> 0 | G504: =D504*0.95 -> 0 | H504: =D504*1.21 -> 0 | I504: =D503*F503 -> 0
D505: =C505*1.4 -> 0 | E505: =D505-C505 -> 0 | G505: =D505*0.95 -> 0 | H505: =D505*1.21 -> 0 | I505: =D504*F504 -> 0
D506: =C506*1.4 -> 0 | E506: =D506-C506 -> 0 | G506: =D506*0.95 -> 0 | H506: =D506*1.21 -> 0 | I506: =D505*F505 -> 0
D507: =C507*1.4 -> 0 | E507: =D507-C507 -> 0 | G507: =D507*0.95 -> 0 | H507: =D507*1.21 -> 0 | I507: =D506*F506 -> 0
D508: =C508*1.4 -> 0 | E508: =D508-C508 -> 0 | G508: =D508*0.95 -> 0 | H508: =D508*1.21 -> 0 | I508: =D507*F507 -> 0
... D859: =C859*1.4 -> 0 | E859: =D859-C859 -> 0 | G859: =D859*0.95 -> 0 | H859: =D859*1.21 -> 0 | I859: =D858*F858 -> 0
I860: =D859*F859 -> 0
I861: =D860*F860 -> 0

Sheet Electroventilador
A1: {=_xlfn._xlws.FILTER(A5:H147,ISNUMBER(SEARCH(B2,A5:A147)))} -> #VALUE!
A2: BUSCAR =
A4: CODIGO | B4: PRODUCTO | C4: FABRICA | D4: PUBLICO | E4: GANANCIA | F4: STOCK | G4: DESC. 5 % | H4: IVA 21 %
A5: OMER08EV'226 | B5: ELECTRO CHEVROLET CORSA 2 1.8 NAFTA 2-12 FIAT PALIO FIRE 1.3 | E5: =D5-C5 -> 0 | F5: 4 | G5: =D5*0.95 -> 0 | H5: =D5*1.21 -> 0
A6: OMER08EV'280 | B6: ELECTRO PEUGEOT PARTNER CITROEN BERLINGO 1.6 16V HDI 10-> | C6: 75508 | D6: =C6*1.4 -> 105711.2 | E6: =D6-C6 -> 30203.2 | F6: 4 | G6: =D6*0.95 -> 100425.64 | H6: =D6*1.21 -> 127910.55
A7: OMER08EV'275 | B7: ELECTRO VW FOX SURAN GOL TREND VOYAGE C/A.A | C7: 107949 | D7: =C7*1.4 -> 151128.6 | E7: =D7-C7 -> 43179.6 | F7: 1 | G7: =D7*0.95 -> 143572.17 | H7: =D7*1.21 -> 182865.61
A8: 13790334624 | B8: ELECTRO RENAULT MEGANE III CLIO II KANGOO LOGAN SANDERO | C8: 55932 | D8: =C8*1.4 -> 78304.8 | E8: =D8-C8 -> 22372.8 | F8: 8 | G8: =D8*0.95 -> 74389.56 | H8: =D8*1.21 -> 94748.808
A9: OMER08EV'212 | B9: ELECTROVENTILADOR PEUGEOT 206 1.6 C/A.A. 207 (FICHA NUEVA) | C9: 61525 | D9: =C9*1.4 -> 86135 | E9: =D9-C9 -> 24610 | F9: 8 | G9: =D9*0.95 -> 81828.25 | H9: =D9*1.21 -> 104223.35
A10: OMER08EV'275 | B10: ELECTROVENTILADOR VW FOX SURAN GOL TREND VOYAGE C/A.A. | C10: 107949 | D10: =C10*1.4 -> 151128.6 | E10: =D10-C10 -> 43179.6 | F10: 6 | G10: =D10*0.95 -> 143572.17 | H10: =D10*1.21 -> 182865.61
A11: OMER08EV-462 | B11: ELECTROVENTILADOR VW FOX SURAN GOL TREND VOYAGE C/A.A | C11: 53135 | D11: =C11*1.4 -> 74389 | E11: =D11-C11 -> 21254 | F11: 1 | G11: =D11*0.95 -> 70669.55 | H11: =D11*1.21 -> 90010.69
A12: OMER08EV'436 | B12: ELECTROVENTILADOR CHEVROLET OPEL ASTRA ZAFIRA VECTRA | C12: 60507 | D12: =C12*1.4 -> 84709.8 | E12: =D12-C12 -> 24202.8 | F12: 4 | G12: =D12*0.95 -> 80474.31 | H12: =D12*1.21 -> 102498.86
A13: OMER08EV'180 | B13: ELECTRO CHEVROLET ASTRA VW GOL SAVEIRO III IV POINTER C/A.A. | C13: 51457 | D13: =C13*1.4 -> 72039.8 | E13: =D13-C13 -> 20582.8 | F13: 4 | G13: =D13*0.95 -> 68437.81 | H13: =D13*1.21 -> 87168.158
A14: OMER08EV'434 | B14: ELECTRO CHEVROLET CORSA II 1.8 8V 04-> (FICHA C/RESISTENCIA) | C14: 51830 | D14: =C14*1.4 -> 72562 | E14: =D14-C14 -> 20732 | F14: 3 | G14: =D14*0.95 -> 68933.9 | H14: =D14*1.21 -> 87800.02
A15: WT'7331 | B15: CHEVROLET CORSA CLASSIC SPIRIT COMP. 1.4 2012+ WETZ | D15: =C15*1.4 -> 0 | E15: =D15-C15 -> 0 | F15: 1 | G15: =D15*0.95 -> 0 | H15: =D15*1.21 -> 0
A16: OMER08EV241 | B16: ELECTROVENTILADOR VW FOX SURAN MOTOR PRINCIPAL | C16: 93966 | D16: =C16*1.4 -> 131552.4 | E16: =D16-C16 -> 37586.4 | F16: 3 | G16: =D16*0.95 -> 124974.78 | H16: =D16*1.21 -> 159178.4
A17: OMER08EV'598 | B17: VOLSWAGEN POLO 1.6 15+ | D17: =C17*1.4 -> 0 | E17: =D17-C17 -> 0 | F17: 1 | G17: =D17*0.95 -> 0 | H17: =D17*1.21 -> 0
A18: 13790334637 | B18: ELECTROVENTILADOR VW GOL III SAVEIRO III IV POINTER S/A.A. | D18: =C18*1.4 -> 0 | E18: =D18-C18 -> 0 | F18: 1 | G18: =D18*0.95 -> 0 | H18: =D18*1.21 -> 0
A19: 1590344825 | B19: ELECTROVENTILADOR CHEVROLET ASTRA ZAFIRA | C19: 68436 | D19: =C19*1.4 -> 95810.4 | E19: =D19-C19 -> 27374.4 | F19: 1 | G19: =D19*0.95 -> 91019.88 | H19: =D19*1.21 -> 115930.58
A20: OMER08EV'316 | B20: ELECTROVENTILADOR CHEV. SONIC SPIN ONIX PRISMA COBALT | C20: 87254 | D20: =C20*1.4 -> 122155.6 | E20: =D20-C20 -> 34901.6 | F20: 2 | G20: =D20*0.95 -> 116047.82 | H20: =D20*1.21 -> 147808.28
A21: OMER08EV'459 | B21: ELECTRO CHEV ONIX PRISMA COBALT SONIC SPIN TRACKER | C21: 66447 | D21: =C21*1.4 -> 93025.8 | E21: =D21-C21 -> 26578.8 | F21: 2 | G21: =D21*0.95 -> 88374.51 | H21: =D21*1.21 -> 112561.22
A22: OMER08EV'582 | B22: ELECTROVENTILADOR FORD ECOSPORT KINETIC 2013 | C22: 53135 | D22: =C22*1.4 -> 74389 | E22: =D22-C22 -> 21254 | F22: 3 | G22: =D22*0.95 -> 70669.55 | H22: =D22*1.21 -> 90010.69
A23: OMER08EV'225 | B23: ELECTROVENTILADOR FORD ECOSPORT FIESTA MAX ONE | C23: 59864 | D23: =C23*1.4 -> 83809.6 | E23: =D23-C23 -> 23945.6 | F23: 5 | G23: =D23*0.95 -> 79619.12 | H23: =D23*1.21 -> 101409.62
A24: OMER08EV'583 | B24: ELECTROVENTILADOR FORD FIESTA KINETIC 1.6 10->13 | C24: 53695 | D24: =C24*1.4 -> 75173 | E24: =D24-C24 -> 21478 | F24: 4 | G24: =D24*0.95 -> 71414.35 | H24: =D24*1.21 -> 90959.33
B25: ELECTRO GATE CLIO II | D25: =C25*1.4 -> 0 | E25: =D25-C25 -> 0 | F25: 1 | G25: =D25*0.95 -> 0 | H25: =D25*1.21 -> 0
B26: ELECTRO DUSTER OROCH | D26: =C26*1.4 -> 0 | E26: =D26-C26 -> 0 | F26: 1 | G26: =D26*0.95 -> 0 | H26: =D26*1.21 -> 0
A27: 13790338825 | B27: ELECTROVENTILADOR VOLKSWAGEN BORA AUTOMATICO | C27: 84191 | D27: =C27*1.4 -> 117867.4 | E27: =D27-C27 -> 33676.4 | F27: 3 | G27: =D27*0.95 -> 111974.03 | H27: =D27*1.21 -> 142619.55
A28: 1590344821 | B28: ELECTROVENTILADOR VW BORA GOLF AUDI A3 MOTOR PRINCIPAL | C28: 96456 | D28: =C28*1.4 -> 135038.4 | E28: =D28-C28 -> 38582.4 | F28: 1 | G28: =D28*0.95 -> 128286.48 | H28: =D28*1.21 -> 163396.46
A29: OMER08EV'279 | B29: ELECTROVENTILADOR VW GOLF IV BORA C/A.A. ´AUXILIAR´ HELICE CHICA | C29: 83339 | D29: =C29*1.4 -> 116674.6 | E29: =D29-C29 -> 33335.6 | F29: 1 | G29: =D29*0.95 -> 110840.87 | H29: =D29*1.21 -> 141176.27
A30: OMER08EV'470 | B30: ELECTROVENTILADOR CHEV SONIC SPIN COBALT ONIX PRISMA C/ENCAUZADOR | C30: 86965 | D30: =C30*1.4 -> 121751 | E30: =D30-C30 -> 34786 | F30: 6 | G30: =D30*0.95 -> 115663.45 | H30: =D30*1.21 -> 147318.71
A31: 13790338810 | B31: ELECTROVENTILADOR FIAT PALIO SIENA C/ENCAUZADOR | C31: 93966 | D31: =C31*1.4 -> 131552.4 | E31: =D31-C31 -> 37586.4 | F31: 1 | G31: =D31*0.95 -> 124974.78 | H31: =D31*1.21 -> 159178.4
A32: OMER08EV'448 | B32: ELECTRO FIAT PALIO FIRE STRADA SIENA C/ENCAUZADOR | C32: 87503 | D32: =C32*1.4 -> 122504.2 | E32: =D32-C32 -> 35001.2 | F32: 2 | G32: =D32*0.95 -> 116378.99 | H32: =D32*1.21 -> 148230.08
A33: 1590371340 | B33: ELECTROVENTILADOR FIAT PALIO SIENA C/A.A TIPO GATE | C33: 84636 | D33: =C33*1.4 -> 118490.4 | E33: =D33-C33 -> 33854.4 | F33: 1 | G33: =D33*0.95 -> 112565.88 | H33: =D33*1.21 -> 143373.38
A34: OMER3115 | B34: ELECTRO FIAT PALIO 1.3 Y 1.0 S/AA | D34: =C34*1.4 -> 0 | E34: =D34-C34 -> 0 | F34: 1 | G34: =D34*0.95 -> 0 | H34: =D34*1.21 -> 0
A35: 1590371338 | B35: ELECTROVENTILADOR FIAT TORO 2.0 500X | C35: 72756 | D35: =C35*1.4 -> 101858.4 | E35: =D35-C35 -> 29102.4 | F35: 1 | G35: =D35*0.95 -> 96765.48 | H35: =D35*1.21 -> 123248.66
A36: 08EV-919 | B36: ELECTROVENTILADOR UNIVERSAL 24V 12" ASPAS RECTAS | C36: 94635 | D36: =C36*1.4 -> 132489 | E36: =D36-C36 -> 37854 | F36: 1 | G36: =D36*0.95 -> 125864.55 | H36: =D36*1.21 -> 160311.69
A37: 16790343892 | B37: ELECTROVENTILADOR 12V UNIVERSAL 10" EXTRACHATO | C37: 40292 | D37: =C37*1.4 -> 56408.8 | E37: =D37-C37 -> 16116.8 | F37: 3 | G37: =D37*0.95 -> 53588.36 | H37: =D37*1.21 -> 68254.648
A38: 10590337566 | B38: ELECTROVENTILADOR UNIVERSAL 12" 12V EXTRACHATO CURVO | C38: 45033 | D38: =C38*1.4 -> 63046.2 | E38: =D38-C38 -> 18013.2 | F38: 3 | G38: =D38*0.95 -> 59893.89 | H38: =D38*1.21 -> 76285.902
A39: OMER08EV'913 | B39: ELECTROVENTILADOR UNIVERSAL 24V 12" ASPAS RECTAS | C39: 37613 | D39: =C39*1.4 -> 52658.2 | E39: =D39-C39 -> 15045.2 | F39: 1 | G39: =D39*0.95 -> 50025.29 | H39: =D39*1.21 -> 63716.422
A40: OMER08EV910 | B40: ELECTROVENTILADOR UNIVERSAL 12V 10" ASPAS RECTAS | C40: 35823 | D40: =C40*1.4 -> 50152.2 | E40: =D40-C40 -> 14329.2 | F40: 1 | G40: =D40*0.95 -> 47644.59 | H40: =D40*1.21 -> 60684.162
A41: 1590344820 | B41: ELECTROVENTILADOR C/ENCAUZADOR REN LOGAN SANDERO DUSTER 1.4 1.6 14> | C41: 78429 | D41: =C41*1.4 -> 109800.6 | E41: =D41-C41 -> 31371.6 | F41: 1 | G41: =D41*0.95 -> 104310.57 | H41: =D41*1.21 -> 132858.73
A42: 1590371344 | B42: ELECTROVENTILADOR COMPLETO RENAULT LOGAN OROCH DUSTER 15-> | C42: 109976 | D42: =C42*1.4 -> 153966.4 | E42: =D42-C42 -> 43990.4 | F42: 1 | G42: =D42*0.95 -> 146268.08 | H42: =D42*1.21 -> 186299.34
A43: OMER08EV'528 | B43: ELECTROVENTILADOR C/ENCAUZADOR REN LOGAN SANDERO DUSTER 1.4 1.6 14> | C43: 72991 | D43: =C43*1.4 -> 102187.4 | E43: =D43-C43 -> 29196.4 | F43: 2 | G43: =D43*0.95 -> 97078.03 | H43: =D43*1.21 -> 123646.75
A44: OMER08EV'453 | B44: ELECTROVENTILADOR RENAULT CLIO SYMBOL C/ENCAUZADOR Y RESISTENCIA | C44: 57218 | D44: =C44*1.4 -> 80105.2 | E44: =D44-C44 -> 22887.2 | F44: 1 | G44: =D44*0.95 -> 76099.94 | H44: =D44*1.21 -> 96927.292
A45: OMER08EV'195 | B45: ELECTROVENTILADOR C/ENCAUSADOR REN CLIO 2 GRAND SCENIC KANGOO MEGANE | C45: 79548 | D45: =C45*1.4 -> 111367.2 | E45: =D45-C45 -> 31819.2 | F45: 1 | G45: =D45*0.95 -> 105798.84 | H45: =D45*1.21 -> 134754.31
A46: OMER08EV'580 | B46: ELECTROVENTILADOR FORD FIESTA ECOSPORT1.4 1.6 2.0 | C46: 95085 | D46: =C46*1.4 -> 133119 | E46: =D46-C46 -> 38034 | F46: 1 | G46: =D46*0.95 -> 126463.05 | H46: =D46*1.21 -> 161073.99
A47: PO592CPV | B47: POLEA VISCOSA FORD | D47: =C47*1.4 -> 0 | E47: =D47-C47 -> 0 | F47: 3 | G47: =D47*0.95 -> 0 | H47: =D47*1.21 -> 0
D48: =C48*1.4 -> 0 | E48: =D48-C48 -> 0 | G48: =D48*0.95 -> 0 | H48: =D48*1.21 -> 0
D49: =C49*1.4 -> 0 | E49: =D49-C49 -> 0 | G49: =D49*0.95 -> 0 | H49: =D49*1.21 -> 0
D50: =C50*1.4 -> 0 | E50: =D50-C50 -> 0 | G50: =D50*0.95 -> 0 | H50: =D50*1.21 -> 0
D51: =C51*1.4 -> 0 | E51: =D51-C51 -> 0 | G51: =D51*0.95 -> 0 | H51: =D51*1.21 -> 0
D52: =C52*1.4 -> 0 | E52: =D52-C52 -> 0 | G52: =D52*0.95 -> 0 | H52: =D52*1.21 -> 0
D53: =C53*1.4 -> 0 | E53: =D53-C53 -> 0 | G53: =D53*0.95 -> 0 | H53: =D53*1.21 -> 0
D54: =C54*1.4 -> 0 | E54: =D54-C54 -> 0 | G54: =D54*0.95 -> 0 | H54: =D54*1.21 -> 0
D55: =C55*1.4 -> 0 | E55: =D55-C55 -> 0 | G55: =D55*0.95 -> 0 | H55: =D55*1.21 -> 0
D56: =C56*1.4 -> 0 | E56: =D56-C56 -> 0 | G56: =D56*0.95 -> 0 | H56: =D56*1.21 -> 0
D57: =C57*1.4 -> 0 | E57: =D57-C57 -> 0 | G57: =D57*0.95 -> 0 | H57: =D57*1.21 -> 0
D58: =C58*1.4 -> 0 | E58: =D58-C58 -> 0 | G58: =D58*0.95 -> 0 | H58: =D58*1.21 -> 0
D59: =C59*1.4 -> 0 | E59: =D59-C59 -> 0 | G59: =D59*0.95 -> 0 | H59: =D59*1.21 -> 0
... D496: =C496*1.4 -> 0 | E496: =D496-C496 -> 0 | G496: =D496*0.95 -> 0 | H496: =D496*1.21 -> 0
D497: =C497*1.4 -> 0 | E497: =D497-C497 -> 0 | G497: =D497*0.95 -> 0 | H497: =D497*1.21 -> 0 | I497: =D496*F496 -> 0
D498: =C498*1.4 -> 0 | E498: =D498-C498 -> 0 | G498: =D498*0.95 -> 0 | H498: =D498*1.21 -> 0 | I498: =D497*F497 -> 0
D499: =C499*1.4 -> 0 | E499: =D499-C499 -> 0 | G499: =D499*0.95 -> 0 | H499: =D499*1.21 -> 0 | I499: =D498*F498 -> 0
D500: =C500*1.4 -> 0 | E500: =D500-C500 -> 0 | G500: =D500*0.95 -> 0 | H500: =D500*1.21 -> 0 | I500: =D499*F499 -> 0
D501: =C501*1.4 -> 0 | E501: =D501-C501 -> 0 | G501: =D501*0.95 -> 0 | H501: =D501*1.21 -> 0 | I501: =D500*F500 -> 0
D502: =C502*1.4 -> 0 | E502: =D502-C502 -> 0 | G502: =D502*0.95 -> 0 | H502: =D502*1.21 -> 0 | I502: =D501*F501 -> 0
D503: =C503*1.4 -> 0 | E503: =D503-C503 -> 0 | G503: =D503*0.95 -> 0 | H503: =D503*1.21 -> 0 | I503: =D502*F502 -> 0
D504: =C504*1.4 -> 0 | E504: =D504-C504 -> 0 | G504: =D504*0.95 -> 0 | H504: =D504*1.21 -> 0 | I504: =D503*F503 -> 0
D505: =C505*1.4 -> 0 | E505: =D505-C505 -> 0 | G505: =D505*0.95 -> 0 | H505: =D505*1.21 -> 0 | I505: =D504*F504 -> 0
D506: =C506*1.4 -> 0 | E506: =D506-C506 -> 0 | G506: =D506*0.95 -> 0 | H506: =D506*1.21 -> 0 | I506: =D505*F505 -> 0
D507: =C507*1.4 -> 0 | E507: =D507-C507 -> 0 | G507: =D507*0.95 -> 0 | H507: =D507*1.21 -> 0 | I507: =D506*F506 -> 0
D508: =C508*1.4 -> 0 | E508: =D508-C508 -> 0 | G508: =D508*0.95 -> 0 | H508: =D508*1.21 -> 0 | I508: =D507*F507 -> 0
... D859: =C859*1.4 -> 0 | E859: =D859-C859 -> 0 | G859: =D859*0.95 -> 0 | H859: =D859*1.21 -> 0 | I859: =D858*F858 -> 0
I860: =D859*F859 -> 0
I861: =D860*F860 -> 0

Sheet OPTICAS
A1: {=_xlfn._xlws.FILTER(A5:H147,ISNUMBER(SEARCH(B2,A5:A147)))} -> #VALUE!
A2: BUSCAR =
A4: CODIGO | B4: PRODUCTO | C4: FABRICA | D4: PUBLICO | E4: GANANCIA | F4: STOCK | G4: DESC. 5 % | H4: IVA 21 %
A5: VIC'777I | B5: FARO IZQ. GOL / SENDA /SAVEIRO 91-95 | E5: =D5-C5 -> 0 | F5: 1 | G5: =D5*0.95 -> 0 | H5: =D5*1.21 -> 0
A6: 330128 | B6: FARO GOL 95-99 SAVEIRO 98-99 AMBAR | D6: =C6*1.4 -> 0 | E6: =D6-C6 -> 0 | F6: 1 | G6: =D6*0.95 -> 0 | H6: =D6*1.21 -> 0
A7: 31194 | B7: FARO FORD F100/150//250/350 DEL. AMBAR C/CHAPA SUJETADORA | D7: =C7*1.4 -> 0 | E7: =D7-C7 -> 0 | F7: 2 | G7: =D7*0.95 -> 0 | H7: =D7*1.21 -> 0
A8: VIC'723I | B8: FARO F-100 93-96 IZQUIERDO | D8: =C8*1.4 -> 0 | E8: =D8-C8 -> 0 | F8: 1 | G8: =D8*0.95 -> 0 | H8: =D8*1.21 -> 0
A9: 12355120D | B9: FARO TRASERO VW 2014+ DERECHO | D9: =C9*1.4 -> 0 | E9: =D9-C9 -> 0 | F9: 2 | G9: =D9*0.95 -> 0 | H9: =D9*1.21 -> 0
A10: 12355120I | B10: FARO TRASERO VW 2014+ IZQUIERDO | D10: =C10*1.4 -> 0 | E10: =D10-C10 -> 0 | F10: 1 | G10: =D10*0.95 -> 0 | H10: =D10*1.21 -> 0
A11: 7798035613335 | B11: FARO TOYOTA HILUX 2011-2015 BICOLOR DERECHO | D11: =C11*1.4 -> 0 | E11: =D11-C11 -> 0 | F11: 2 | G11: =D11*0.95 -> 0 | H11: =D11*1.21 -> 0
A12: 7798035613335 | B12: FARO TOYOTA HILUX 2011-2015 BICOLOR IZQUIERDO | D12: =C12*1.4 -> 0 | E12: =D12-C12 -> 0 | F12: 1 | G12: =D12*0.95 -> 0 | H12: =D12*1.21 -> 0
A13: 53230 | B13: FARO TRASERO TOYOTA HILUX 2001-2005 DERECHO | D13: =C13*1.4 -> 0 | E13: =D13-C13 -> 0 | F13: 2 | G13: =D13*0.95 -> 0 | H13: =D13*1.21 -> 0
A14: 53230 | B14: FARO TRASERO TOYOTA HILUX 2001-2005 IZQUIERDO | D14: =C14*1.4 -> 0 | E14: =D14-C14 -> 0 | F14: 3 | G14: =D14*0.95 -> 0 | H14: =D14*1.21 -> 0
A15: LA-OP021046 | B15: OPTICA FORD RANGER 04->09 | C15: 106365 | D15: =C15*1.4 -> 148911 | E15: =D15-C15 -> 42546 | F15: 1 | G15: =D15*0.95 -> 141465.45 | H15: =D15*1.21 -> 180182.31
A16: 36023 | B16: FARO TRASERO FORD RANGER 2004-2009 HUMO | D16: =C16*1.4 -> 0 | E16: =D16-C16 -> 0 | F16: 1 | G16: =D16*0.95 -> 0 | H16: =D16*1.21 -> 0
A17: 36023 | B17: FARO DELANTERO FORD RANGER 2004-2009 HUMO | D17: =C17*1.4 -> 0 | E17: =D17-C17 -> 0 | F17: 1 | G17: =D17*0.95 -> 0 | H17: =D17*1.21 -> 0
A18: 39013050D | B18: FARO TRASERO TOYOTA HILUX 16+ BI COLOR IZQUIERDO | D18: =C18*1.4 -> 0 | E18: =D18-C18 -> 0 | F18: 2 | G18: =D18*0.95 -> 0 | H18: =D18*1.21 -> 0
A19: 39013050I | B19: FARO TRASERO TOYOTA HILUX 16+ BI COLOR IZQUIERDO | D19: =C19*1.4 -> 0 | E19: =D19-C19 -> 0 | F19: 1 | G19: =D19*0.95 -> 0 | H19: =D19*1.21 -> 0
A20: 036111A | B20: FARO TRASERO FORD RANGER 2010-2012 ACRIL IZQ. | D20: =C20*1.4 -> 0 | E20: =D20-C20 -> 0 | F20: 2 | G20: =D20*0.95 -> 0 | H20: =D20*1.21 -> 0
A21: 036111A | B21: FARO TRASERO FORD RANGER 2010-2012 ACRIL IDERECHO | D21: =C21*1.4 -> 0 | E21: =D21-C21 -> 0 | F21: 2 | G21: =D21*0.95 -> 0 | H21: =D21*1.21 -> 0
A22: 7798035610464 | B22: FARO TRASERO FORD RANGER 2012+ 12-15 IZQ | D22: =C22*1.4 -> 0 | E22: =D22-C22 -> 0 | F22: 4 | G22: =D22*0.95 -> 0 | H22: =D22*1.21 -> 0
A23: 7798035610464 | B23: FARO TRASERO FORD RANGER 2012+ 12-15 DERECHO | D23: =C23*1.4 -> 0 | E23: =D23-C23 -> 0 | F23: 4 | G23: =D23*0.95 -> 0 | H23: =D23*1.21 -> 0
B24: FARO TRASERO FORD RANGER 2017-2023 P/ BULBO IZQ. | D24: =C24*1.4 -> 0 | E24: =D24-C24 -> 0 | F24: 1 | G24: =D24*0.95 -> 0 | H24: =D24*1.21 -> 0
B25: FARO TRASERO GOL POWER 2005-2013 | C25: 30000 | D25: =C25*1.4 -> 42000 | E25: =D25-C25 -> 12000 | F25: 2 | G25: =D25*0.95 -> 39900 | H25: =D25*1.21 -> 50820
D26: =C26*1.4 -> 0 | E26: =D26-C26 -> 0 | G26: =D26*0.95 -> 0 | H26: =D26*1.21 -> 0
D27: =C27*1.4 -> 0 | E27: =D27-C27 -> 0 | G27: =D27*0.95 -> 0 | H27: =D27*1.21 -> 0
D28: =C28*1.4 -> 0 | E28: =D28-C28 -> 0 | G28: =D28*0.95 -> 0 | H28: =D28*1.21 -> 0
D29: =C29*1.4 -> 0 | E29: =D29-C29 -> 0 | G29: =D29*0.95 -> 0 | H29: =D29*1.21 -> 0
D30: =C30*1.4 -> 0 | E30: =D30-C30 -> 0 | G30: =D30*0.95 -> 0 | H30: =D30*1.21 -> 0
D31: =C31*1.4 -> 0 | E31: =D31-C31 -> 0 | G31: =D31*0.95 -> 0 | H31: =D31*1.21 -> 0
D32: =C32*1.4 -> 0 | E32: =D32-C32 -> 0 | G32: =D32*0.95 -> 0 | H32: =D32*1.21 -> 0
D33: =C33*1.4 -> 0 | E33: =D33-C33 -> 0 | G33: =D33*0.95 -> 0 | H33: =D33*1.21 -> 0
D34: =C34*1.4 -> 0 | E34: =D34-C34 -> 0 | G34: =D34*0.95 -> 0 | H34: =D34*1.21 -> 0
D35: =C35*1.4 -> 0 | E35: =D35-C35 -> 0 | G35: =D35*0.95 -> 0 | H35: =D35*1.21 -> 0
D36: =C36*1.4 -> 0 | E36: =D36-C36 -> 0 | G36: =D36*0.95 -> 0 | H36: =D36*1.21 -> 0
D37: =C37*1.4 -> 0 | E37: =D37-C37 -> 0 | G37: =D37*0.95 -> 0 | H37: =D37*1.21 -> 0
... D496: =C496*1.4 -> 0 | E496: =D496-C496 -> 0 | G496: =D496*0.95 -> 0 | H496: =D496*1.21 -> 0
D497: =C497*1.4 -> 0 | E497: =D497-C497 -> 0 | G497: =D497*0.95 -> 0 | H497: =D497*1.21 -> 0 | I497: =D496*F496 -> 0
D498: =C498*1.4 -> 0 | E498: =D498-C498 -> 0 | G498: =D498*0.95 -> 0 | H498: =D498*1.21 -> 0 | I498: =D497*F497 -> 0
D499: =C499*1.4 -> 0 | E499: =D499-C499 -> 0 | G499: =D499*0.95 -> 0 | H499: =D499*1.21 -> 0 | I499: =D498*F498 -> 0
D500: =C500*1.4 -> 0 | E500: =D500-C500 -> 0 | G500: =D500*0.95 -> 0 | H500: =D500*1.21 -> 0 | I500: =D499*F499 -> 0
D501: =C501*1.4 -> 0 | E501: =D501-C501 -> 0 | G501: =D501*0.95 -> 0 | H501: =D501*1.21 -> 0 | I501: =D500*F500 -> 0
D502: =C502*1.4 -> 0 | E502: =D502-C502 -> 0 | G502: =D502*0.95 -> 0 | H502: =D502*1.21 -> 0 | I502: =D501*F501 -> 0
D503: =C503*1.4 -> 0 | E503: =D503-C503 -> 0 | G503: =D503*0.95 -> 0 | H503: =D503*1.21 -> 0 | I503: =D502*F502 -> 0
D504: =C504*1.4 -> 0 | E504: =D504-C504 -> 0 | G504: =D504*0.95 -> 0 | H504: =D504*1.21 -> 0 | I504: =D503*F503 -> 0
D505: =C505*1.4 -> 0 | E505: =D505-C505 -> 0 | G505: =D505*0.95 -> 0 | H505: =D505*1.21 -> 0 | I505: =D504*F504 -> 0
D506: =C506*1.4 -> 0 | E506: =D506-C506 -> 0 | G506: =D506*0.95 -> 0 | H506: =D506*1.21 -> 0 | I506: =D505*F505 -> 0
D507: =C507*1.4 -> 0 | E507: =D507-C507 -> 0 | G507: =D507*0.95 -> 0 | H507: =D507*1.21 -> 0 | I507: =D506*F506 -> 0
D508: =C508*1.4 -> 0 | E508: =D508-C508 -> 0 | G508: =D508*0.95 -> 0 | H508: =D508*1.21 -> 0 | I508: =D507*F507 -> 0
... D859: =C859*1.4 -> 0 | E859: =D859-C859 -> 0 | G859: =D859*0.95 -> 0 | H859: =D859*1.21 -> 0 | I859: =D858*F858 -> 0
I860: =D859*F859 -> 0
I861: =D860*F860 -> 0

Sheet copiar
A1: {=_xlfn._xlws.FILTER(A5:H147,ISNUMBER(SEARCH(B2,A5:A147)))} -> #VALUE!
A2: BUSCAR =
A4: CODIGO | B4: PRODUCTO | C4: FABRICA | D4: PUBLICO | E4: GANANCIA | F4: STOCK | G4: DESC. 5 % | H4: IVA 21 %
E5: =D5-C5 -> 0 | G5: =D5*0.95 -> 0 | H5: =D5*1.21 -> 0
D6: =C6*1.4 -> 0 | E6: =D6-C6 -> 0 | G6: =D6*0.95 -> 0 | H6: =D6*1.21 -> 0
D7: =C7*1.4 -> 0 | E7: =D7-C7 -> 0 | G7: =D7*0.95 -> 0 | H7: =D7*1.21 -> 0
D8: =C8*1.4 -> 0 | E8: =D8-C8 -> 0 | G8: =D8*0.95 -> 0 | H8: =D8*1.21 -> 0
D9: =C9*1.4 -> 0 | E9: =D9-C9 -> 0 | G9: =D9*0.95 -> 0 | H9: =D9*1.21 -> 0
D10: =C10*1.4 -> 0 | E10: =D10-C10 -> 0 | G10: =D10*0.95 -> 0 | H10: =D10*1.21 -> 0
D11: =C11*1.4 -> 0 | E11: =D11-C11 -> 0 | G11: =D11*0.95 -> 0 | H11: =D11*1.21 -> 0
D12: =C12*1.4 -> 0 | E12: =D12-C12 -> 0 | G12: =D12*0.95 -> 0 | H12: =D12*1.21 -> 0
D13: =C13*1.4 -> 0 | E13: =D13-C13 -> 0 | G13: =D13*0.95 -> 0 | H13: =D13*1.21 -> 0
D14: =C14*1.4 -> 0 | E14: =D14-C14 -> 0 | G14: =D14*0.95 -> 0 | H14: =D14*1.21 -> 0
D15: =C15*1.4 -> 0 | E15: =D15-C15 -> 0 | G15: =D15*0.95 -> 0 | H15: =D15*1.21 -> 0
D16: =C16*1.4 -> 0 | E16: =D16-C16 -> 0 | G16: =D16*0.95 -> 0 | H16: =D16*1.21 -> 0
D17: =C17*1.4 -> 0 | E17: =D17-C17 -> 0 | G17: =D17*0.95 -> 0 | H17: =D17*1.21 -> 0
... D496: =C496*1.4 -> 0 | E496: =D496-C496 -> 0 | G496: =D496*0.95 -> 0 | H496: =D496*1.21 -> 0
D497: =C497*1.4 -> 0 | E497: =D497-C497 -> 0 | G497: =D497*0.95 -> 0 | H497: =D497*1.21 -> 0 | I497: =D496*F496 -> 0
D498: =C498*1.4 -> 0 | E498: =D498-C498 -> 0 | G498: =D498*0.95 -> 0 | H498: =D498*1.21 -> 0 | I498: =D497*F497 -> 0
D499: =C499*1.4 -> 0 | E499: =D499-C499 -> 0 | G499: =D499*0.95 -> 0 | H499: =D499*1.21 -> 0 | I499: =D498*F498 -> 0
D500: =C500*1.4 -> 0 | E500: =D500-C500 -> 0 | G500: =D500*0.95 -> 0 | H500: =D500*1.21 -> 0 | I500: =D499*F499 -> 0
D501: =C501*1.4 -> 0 | E501: =D501-C501 -> 0 | G501: =D501*0.95 -> 0 | H501: =D501*1.21 -> 0 | I501: =D500*F500 -> 0
D502: =C502*1.4 -> 0 | E502: =D502-C502 -> 0 | G502: =D502*0.95 -> 0 | H502: =D502*1.21 -> 0 | I502: =D501*F501 -> 0
D503: =C503*1.4 -> 0 | E503: =D503-C503 -> 0 | G503: =D503*0.95 -> 0 | H503: =D503*1.21 -> 0 | I503: =D502*F502 -> 0
D504: =C504*1.4 -> 0 | E504: =D504-C504 -> 0 | G504: =D504*0.95 -> 0 | H504: =D504*1.21 -> 0 | I504: =D503*F503 -> 0
D505: =C505*1.4 -> 0 | E505: =D505-C505 -> 0 | G505: =D505*0.95 -> 0 | H505: =D505*1.21 -> 0 | I505: =D504*F504 -> 0
D506: =C506*1.4 -> 0 | E506: =D506-C506 -> 0 | G506: =D506*0.95 -> 0 | H506: =D506*1.21 -> 0 | I506: =D505*F505 -> 0
D507: =C507*1.4 -> 0 | E507: =D507-C507 -> 0 | G507: =D507*0.95 -> 0 | H507: =D507*1.21 -> 0 | I507: =D506*F506 -> 0
D508: =C508*1.4 -> 0 | E508: =D508-C508 -> 0 | G508: =D508*0.95 -> 0 | H508: =D508*1.21 -> 0 | I508: =D507*F507 -> 0
... D859: =C859*1.4 -> 0 | E859: =D859-C859 -> 0 | G859: =D859*0.95 -> 0 | H859: =D859*1.21 -> 0 | I859: =D858*F858 -> 0
I860: =D859*F859 -> 0
I861: =D860*F860 -> 0

Sheet Ajustes
A1: AJUSTES PERMANENTES DE PRODUCTOS
A2: Copiá “FILA ORIGINAL” desde el buscador. Ingresá una sola vez cada fila y completá NUEVO FABRICA y/o NUEVO STOCK.
A4: FILA ORIGINAL | B4: CODIGO | C4: PRODUCTO | D4: NUEVO FABRICA | E4: NUEVO STOCK
B5: {=IF(A5="","",IFERROR(INDEX(EQUIPAMIENTO!$A:$A,A5),"FILA INVÁLIDA"))} | C5: {=IF(A5="","",IFERROR(INDEX(EQUIPAMIENTO!$B:$B,A5),""))}
B6: {=IF(A6="","",IFERROR(INDEX(EQUIPAMIENTO!$A:$A,A6),"FILA INVÁLIDA"))} | C6: {=IF(A6="","",IFERROR(INDEX(EQUIPAMIENTO!$B:$B,A6),""))}
B7: {=IF(A7="","",IFERROR(INDEX(EQUIPAMIENTO!$A:$A,A7),"FILA INVÁLIDA"))} | C7: {=IF(A7="","",IFERROR(INDEX(EQUIPAMIENTO!$B:$B,A7),""))}
B8: {=IF(A8="","",IFERROR(INDEX(EQUIPAMIENTO!$A:$A,A8),"FILA INVÁLIDA"))} | C8: {=IF(A8="","",IFERROR(INDEX(EQUIPAMIENTO!$B:$B,A8),""))}
B9: {=IF(A9="","",IFERROR(INDEX(EQUIPAMIENTO!$A:$A,A9),"FILA INVÁLIDA"))} | C9: {=IF(A9="","",IFERROR(INDEX(EQUIPAMIENTO!$B:$B,A9),""))}
B10: {=IF(A10="","",IFERROR(INDEX(EQUIPAMIENTO!$A:$A,A10),"FILA INVÁLIDA"))} | C10: {=IF(A10="","",IFERROR(INDEX(EQUIPAMIENTO!$B:$B,A10),""))}
B11: {=IF(A11="","",IFERROR(INDEX(EQUIPAMIENTO!$A:$A,A11),"FILA INVÁLIDA"))} | C11: {=IF(A11="","",IFERROR(INDEX(EQUIPAMIENTO!$B:$B,A11),""))}
B12: {=IF(A12="","",IFERROR(INDEX(EQUIPAMIENTO!$A:$A,A12),"FILA INVÁLIDA"))} | C12: {=IF(A12="","",IFERROR(INDEX(EQUIPAMIENTO!$B:$B,A12),""))}
B13: {=IF(A13="","",IFERROR(INDEX(EQUIPAMIENTO!$A:$A,A13),"FILA INVÁLIDA"))} | C13: {=IF(A13="","",IFERROR(INDEX(EQUIPAMIENTO!$B:$B,A13),""))}
B14: {=IF(A14="","",IFERROR(INDEX(EQUIPAMIENTO!$A:$A,A14),"FILA INVÁLIDA"))} | C14: {=IF(A14="","",IFERROR(INDEX(EQUIPAMIENTO!$B:$B,A14),""))}
B15: {=IF(A15="","",IFERROR(INDEX(EQUIPAMIENTO!$A:$A,A15),"FILA INVÁLIDA"))} | C15: {=IF(A15="","",IFERROR(INDEX(EQUIPAMIENTO!$B:$B,A15),""))}
B16: {=IF(A16="","",IFERROR(INDEX(EQUIPAMIENTO!$A:$A,A16),"FILA INVÁLIDA"))} | C16: {=IF(A16="","",IFERROR(INDEX(EQUIPAMIENTO!$B:$B,A16),""))}
... B104: {=IF(A104="","",IFERROR(INDEX(EQUIPAMIENTO!$A:$A,A104),"FILA INVÁLIDA"))} | C104: {=IF(A104="","",IFERROR(INDEX(EQUIPAMIENTO!$B:$B,A104),""))}
